{
"meta":{"test_sets":[],"test_metrics":[],"learn_metrics":[{"best_value":"Min","name":"Logloss"}],"launch_mode":"Train","parameters":"","iteration_count":1000,"learn_sets":["learn"],"name":"experiment"},
"iterations":[
{"learn":[0.6179553125],"iteration":0,"passed_time":0.02097773027,"remaining_time":20.95675254},
{"learn":[0.5624902808],"iteration":1,"passed_time":0.04129944852,"remaining_time":20.60842481},
{"learn":[0.5138743264],"iteration":2,"passed_time":0.06169830804,"remaining_time":20.50440437},
{"learn":[0.47119856],"iteration":3,"passed_time":0.08555452603,"remaining_time":21.30307698},
{"learn":[0.4345122654],"iteration":4,"passed_time":0.1077039994,"remaining_time":21.43309588},
{"learn":[0.4043199889],"iteration":5,"passed_time":0.1329434153,"remaining_time":22.02429247},
{"learn":[0.377234638],"iteration":6,"passed_time":0.1567208673,"remaining_time":22.23197446},
{"learn":[0.355241435],"iteration":7,"passed_time":0.1806594529,"remaining_time":22.40177216},
{"learn":[0.3354379123],"iteration":8,"passed_time":0.2015329139,"remaining_time":22.19101308},
{"learn":[0.3196153066],"iteration":9,"passed_time":0.2258484382,"remaining_time":22.35899538},
{"learn":[0.3065669311],"iteration":10,"passed_time":0.248482071,"remaining_time":22.34079711},
{"learn":[0.2939515328],"iteration":11,"passed_time":0.2738092168,"remaining_time":22.54362552},
{"learn":[0.2832806458],"iteration":12,"passed_time":0.2982223772,"remaining_time":22.64196049},
{"learn":[0.2736318885],"iteration":13,"passed_time":0.3220583658,"remaining_time":22.68211062},
{"learn":[0.2661489208],"iteration":14,"passed_time":0.346770859,"remaining_time":22.7712864},
{"learn":[0.2597527286],"iteration":15,"passed_time":0.3747939307,"remaining_time":23.04982674},
{"learn":[0.2539661433],"iteration":16,"passed_time":0.4015481023,"remaining_time":23.21892851},
{"learn":[0.2489081497],"iteration":17,"passed_time":0.4274729987,"remaining_time":23.32102693},
{"learn":[0.2450702605],"iteration":18,"passed_time":0.4531378402,"remaining_time":23.39622217},
{"learn":[0.2407001091],"iteration":19,"passed_time":0.4811184205,"remaining_time":23.5748026},
{"learn":[0.2373851902],"iteration":20,"passed_time":0.5078235422,"remaining_time":23.67424989},
{"learn":[0.2342454948],"iteration":21,"passed_time":0.5360118833,"remaining_time":23.82816463},
{"learn":[0.2320031558],"iteration":22,"passed_time":0.5645402323,"remaining_time":23.98068726},
{"learn":[0.2292475268],"iteration":23,"passed_time":0.5900881497,"remaining_time":23.99691809},
{"learn":[0.227464596],"iteration":24,"passed_time":0.6174566247,"remaining_time":24.08080836},
{"learn":[0.2254275571],"iteration":25,"passed_time":0.6418719347,"remaining_time":24.04551017},
{"learn":[0.2238922391],"iteration":26,"passed_time":0.6683593202,"remaining_time":24.08568957},
{"learn":[0.2223341992],"iteration":27,"passed_time":0.6952635187,"remaining_time":24.13557644},
{"learn":[0.2207363445],"iteration":28,"passed_time":0.7237688879,"remaining_time":24.23377897},
{"learn":[0.2195637572],"iteration":29,"passed_time":0.7511416214,"remaining_time":24.28691243},
{"learn":[0.2183426804],"iteration":30,"passed_time":0.7809960527,"remaining_time":24.412425},
{"learn":[0.2171352751],"iteration":31,"passed_time":0.8076162077,"remaining_time":24.43039028},
{"learn":[0.2164322208],"iteration":32,"passed_time":0.8382487679,"remaining_time":24.56322905},
{"learn":[0.2156163656],"iteration":33,"passed_time":0.8725392056,"remaining_time":24.79037861},
{"learn":[0.2147082988],"iteration":34,"passed_time":0.9086838215,"remaining_time":25.05371108},
{"learn":[0.2139971895],"iteration":35,"passed_time":0.9407802066,"remaining_time":25.19200331},
{"learn":[0.2132668418],"iteration":36,"passed_time":0.9710471886,"remaining_time":25.27347142},
{"learn":[0.2128364592],"iteration":37,"passed_time":1.002611396,"remaining_time":25.38189902},
{"learn":[0.2123890861],"iteration":38,"passed_time":1.033641323,"remaining_time":25.46998235},
{"learn":[0.2117761719],"iteration":39,"passed_time":1.060902786,"remaining_time":25.46166687},
{"learn":[0.2113160282],"iteration":40,"passed_time":1.09294246,"remaining_time":25.56419071},
{"learn":[0.2105531735],"iteration":41,"passed_time":1.124586447,"remaining_time":25.65128135},
{"learn":[0.2099332702],"iteration":42,"passed_time":1.157766726,"remaining_time":25.76704086},
{"learn":[0.209517354],"iteration":43,"passed_time":1.189126262,"remaining_time":25.8364706},
{"learn":[0.2089734184],"iteration":44,"passed_time":1.224383681,"remaining_time":25.98414255},
{"learn":[0.2086491305],"iteration":45,"passed_time":1.25761296,"remaining_time":26.08179922},
{"learn":[0.2081991698],"iteration":46,"passed_time":1.290294764,"remaining_time":26.16278532},
{"learn":[0.2075838441],"iteration":47,"passed_time":1.317930246,"remaining_time":26.13894987},
{"learn":[0.207273692],"iteration":48,"passed_time":1.350062451,"remaining_time":26.20223247},
{"learn":[0.2069940308],"iteration":49,"passed_time":1.380806889,"remaining_time":26.23533089},
{"learn":[0.2066703502],"iteration":50,"passed_time":1.414983321,"remaining_time":26.32978768},
{"learn":[0.2063229702],"iteration":51,"passed_time":1.443775649,"remaining_time":26.32114069},
{"learn":[0.2059343383],"iteration":52,"passed_time":1.478547766,"remaining_time":26.41857989},
{"learn":[0.2057471575],"iteration":53,"passed_time":1.509916382,"remaining_time":26.4514981},
{"learn":[0.2052492787],"iteration":54,"passed_time":1.539117711,"remaining_time":26.44484067},
{"learn":[0.2046926992],"iteration":55,"passed_time":1.569452551,"remaining_time":26.45648585},
{"learn":[0.204392774],"iteration":56,"passed_time":1.598873363,"remaining_time":26.45153652},
{"learn":[0.2040779568],"iteration":57,"passed_time":1.63435684,"remaining_time":26.54420937},
{"learn":[0.2037558378],"iteration":58,"passed_time":1.66565956,"remaining_time":26.5658584},
{"learn":[0.2036108923],"iteration":59,"passed_time":1.696138258,"remaining_time":26.57283271},
{"learn":[0.2033606394],"iteration":60,"passed_time":1.72918851,"remaining_time":26.61816411},
{"learn":[0.2031679974],"iteration":61,"passed_time":1.762676816,"remaining_time":26.6675944},
{"learn":[0.2030238263],"iteration":62,"passed_time":1.796152682,"remaining_time":26.71420734},
{"learn":[0.2026090811],"iteration":63,"passed_time":1.825047233,"remaining_time":26.69131579},
{"learn":[0.2021017276],"iteration":64,"passed_time":1.85505166,"remaining_time":26.68420464},
{"learn":[0.201566378],"iteration":65,"passed_time":1.886086774,"remaining_time":26.69098556},
{"learn":[0.2013074132],"iteration":66,"passed_time":1.917299416,"remaining_time":26.69910978},
{"learn":[0.2010922424],"iteration":67,"passed_time":1.94594404,"remaining_time":26.67088008},
{"learn":[0.2009423792],"iteration":68,"passed_time":1.977765097,"remaining_time":26.68549718},
{"learn":[0.2007888511],"iteration":69,"passed_time":2.009856699,"remaining_time":26.70238186},
{"learn":[0.2006549436],"iteration":70,"passed_time":2.04015309,"remaining_time":26.69439747},
{"learn":[0.2003850527],"iteration":71,"passed_time":2.070285411,"remaining_time":26.68367863},
{"learn":[0.20012178],"iteration":72,"passed_time":2.100097569,"remaining_time":26.66836228},
{"learn":[0.2000373233],"iteration":73,"passed_time":2.132157952,"remaining_time":26.68078735},
{"learn":[0.1999281443],"iteration":74,"passed_time":2.159119714,"remaining_time":26.62914314},
{"learn":[0.1996113808],"iteration":75,"passed_time":2.188249846,"remaining_time":26.60451128},
{"learn":[0.1994695964],"iteration":76,"passed_time":2.219327777,"remaining_time":26.60311088},
{"learn":[0.1992984567],"iteration":77,"passed_time":2.243944686,"remaining_time":26.52457693},
{"learn":[0.1990970697],"iteration":78,"passed_time":2.276257174,"remaining_time":26.53712478},
{"learn":[0.198697679],"iteration":79,"passed_time":2.304425309,"remaining_time":26.50089105},
{"learn":[0.1983631106],"iteration":80,"passed_time":2.329090647,"remaining_time":26.42511487},
{"learn":[0.1979177117],"iteration":81,"passed_time":2.355760527,"remaining_time":26.37302639},
{"learn":[0.1978115628],"iteration":82,"passed_time":2.384220981,"remaining_time":26.341333},
{"learn":[0.1976494449],"iteration":83,"passed_time":2.414465929,"remaining_time":26.32917608},
{"learn":[0.1974885857],"iteration":84,"passed_time":2.442983481,"remaining_time":26.29799865},
{"learn":[0.197254081],"iteration":85,"passed_time":2.473606371,"remaining_time":26.2892584},
{"learn":[0.1969632796],"iteration":86,"passed_time":2.506331534,"remaining_time":26.3020769},
{"learn":[0.1965141057],"iteration":87,"passed_time":2.534796831,"remaining_time":26.26971261},
{"learn":[0.1963658408],"iteration":88,"passed_time":2.56631385,"remaining_time":26.26867322},
{"learn":[0.1959953998],"iteration":89,"passed_time":2.593923016,"remaining_time":26.22744382},
{"learn":[0.1959021418],"iteration":90,"passed_time":2.624183365,"remaining_time":26.21299647},
{"learn":[0.1956173073],"iteration":91,"passed_time":2.65549047,"remaining_time":26.20853638},
{"learn":[0.1955510015],"iteration":92,"passed_time":2.684689611,"remaining_time":26.18294061},
{"learn":[0.1954116213],"iteration":93,"passed_time":2.717205376,"remaining_time":26.18923479},
{"learn":[0.1950530912],"iteration":94,"passed_time":2.744404329,"remaining_time":26.14406229},
{"learn":[0.1946517499],"iteration":95,"passed_time":2.771254231,"remaining_time":26.09597734},
{"learn":[0.1945326715],"iteration":96,"passed_time":2.798686655,"remaining_time":26.05375308},
{"learn":[0.1943201222],"iteration":97,"passed_time":2.828304265,"remaining_time":26.03194334},
{"learn":[0.1940057961],"iteration":98,"passed_time":2.851899471,"remaining_time":25.95516589},
{"learn":[0.193938075],"iteration":99,"passed_time":2.885277408,"remaining_time":25.96749667},
{"learn":[0.1938732619],"iteration":100,"passed_time":2.914470925,"remaining_time":25.94167684},
{"learn":[0.1938152174],"iteration":101,"passed_time":2.945814921,"remaining_time":25.93472352},
{"learn":[0.1937095075],"iteration":102,"passed_time":2.975246872,"remaining_time":25.91064509},
{"learn":[0.1935765786],"iteration":103,"passed_time":3.006203782,"remaining_time":25.89960182},
{"learn":[0.1934521167],"iteration":104,"passed_time":3.042076797,"remaining_time":25.93008318},
{"learn":[0.1930600509],"iteration":105,"passed_time":3.075360974,"remaining_time":25.9374784},
{"learn":[0.1928716265],"iteration":106,"passed_time":3.110611849,"remaining_time":25.96052693},
{"learn":[0.1926819612],"iteration":107,"passed_time":3.142401567,"remaining_time":25.95390923},
{"learn":[0.1926050294],"iteration":108,"passed_time":3.177571677,"remaining_time":25.97446205},
{"learn":[0.1925421467],"iteration":109,"passed_time":3.210636244,"remaining_time":25.97696597},
{"learn":[0.1924773141],"iteration":110,"passed_time":3.2446635,"remaining_time":25.98653921},
{"learn":[0.192253099],"iteration":111,"passed_time":3.309460599,"remaining_time":26.23929475},
{"learn":[0.1921335445],"iteration":112,"passed_time":3.349029663,"remaining_time":26.28840099},
{"learn":[0.1920485481],"iteration":113,"passed_time":3.378885779,"remaining_time":26.26046316},
{"learn":[0.1919213081],"iteration":114,"passed_time":3.414419158,"remaining_time":26.27618222},
{"learn":[0.1916692219],"iteration":115,"passed_time":3.45166636,"remaining_time":26.30407812},
{"learn":[0.1915294477],"iteration":116,"passed_time":3.485376495,"remaining_time":26.3041662},
{"learn":[0.1914599591],"iteration":117,"passed_time":3.518562748,"remaining_time":26.29976563},
{"learn":[0.1912766394],"iteration":118,"passed_time":3.552164845,"remaining_time":26.2979599},
{"learn":[0.1911400109],"iteration":119,"passed_time":3.58735436,"remaining_time":26.30726531},
{"learn":[0.1907628515],"iteration":120,"passed_time":3.616086102,"remaining_time":26.268923},
{"learn":[0.1905845015],"iteration":121,"passed_time":3.646696472,"remaining_time":26.24425822},
{"learn":[0.1905034646],"iteration":122,"passed_time":3.678595194,"remaining_time":26.22868281},
{"learn":[0.1903297395],"iteration":123,"passed_time":3.712717747,"remaining_time":26.22855441},
{"learn":[0.1901251728],"iteration":124,"passed_time":3.745688651,"remaining_time":26.21982055},
{"learn":[0.1900889643],"iteration":125,"passed_time":3.772586178,"remaining_time":26.16857396},
{"learn":[0.1898279713],"iteration":126,"passed_time":3.80613296,"remaining_time":26.16341791},
{"learn":[0.1896904767],"iteration":127,"passed_time":3.839058908,"remaining_time":26.15358881},
{"learn":[0.1896197086],"iteration":128,"passed_time":3.870989029,"remaining_time":26.13667786},
{"learn":[0.1894436214],"iteration":129,"passed_time":3.902001127,"remaining_time":26.11339215},
{"learn":[0.1893280931],"iteration":130,"passed_time":3.928618501,"remaining_time":26.0608357},
{"learn":[0.1891887516],"iteration":131,"passed_time":3.96031094,"remaining_time":26.04204467},
{"learn":[0.1890274796],"iteration":132,"passed_time":3.987939263,"remaining_time":25.99656647},
{"learn":[0.1888925273],"iteration":133,"passed_time":4.019459145,"remaining_time":25.97650463},
{"learn":[0.1887859568],"iteration":134,"passed_time":4.053908049,"remaining_time":25.97504046},
{"learn":[0.1886833164],"iteration":135,"passed_time":4.084325052,"remaining_time":25.9474768},
{"learn":[0.1885749196],"iteration":136,"passed_time":4.11678759,"remaining_time":25.93275686},
{"learn":[0.1885448574],"iteration":137,"passed_time":4.147975868,"remaining_time":25.90982028},
{"learn":[0.1883269601],"iteration":138,"passed_time":4.177352204,"remaining_time":25.87554135},
{"learn":[0.1881946711],"iteration":139,"passed_time":4.20873188,"remaining_time":25.85363869},
{"learn":[0.1881335721],"iteration":140,"passed_time":4.241152739,"remaining_time":25.8379447},
{"learn":[0.1880714713],"iteration":141,"passed_time":4.268499058,"remaining_time":25.79135346},
{"learn":[0.1879088289],"iteration":142,"passed_time":4.299207355,"remaining_time":25.76517974},
{"learn":[0.1878599397],"iteration":143,"passed_time":4.325188036,"remaining_time":25.71083999},
{"learn":[0.18746653],"iteration":144,"passed_time":4.357648826,"remaining_time":25.6951017},
{"learn":[0.187414732],"iteration":145,"passed_time":4.387516586,"remaining_time":25.66396688},
{"learn":[0.1871974318],"iteration":146,"passed_time":4.415664744,"remaining_time":25.62287093},
{"learn":[0.187159841],"iteration":147,"passed_time":4.445814783,"remaining_time":25.59347429},
{"learn":[0.1870656022],"iteration":148,"passed_time":4.477638792,"remaining_time":25.57362827},
{"learn":[0.1869145714],"iteration":149,"passed_time":4.506983979,"remaining_time":25.53957588},
{"learn":[0.1866124536],"iteration":150,"passed_time":4.531459553,"remaining_time":25.47820636},
{"learn":[0.1864433316],"iteration":151,"passed_time":4.56124499,"remaining_time":25.44694573},
{"learn":[0.1864009202],"iteration":152,"passed_time":4.586833741,"remaining_time":25.39247176},
{"learn":[0.1862970382],"iteration":153,"passed_time":4.614924885,"remaining_time":25.35211982},
{"learn":[0.1862571679],"iteration":154,"passed_time":4.64237522,"remaining_time":25.30843265},
{"learn":[0.1862085383],"iteration":155,"passed_time":4.67120405,"remaining_time":25.27241166},
{"learn":[0.1861805947],"iteration":156,"passed_time":4.696805893,"remaining_time":25.21915521},
{"learn":[0.1860655815],"iteration":157,"passed_time":4.722643898,"remaining_time":25.16750736},
{"learn":[0.186015768],"iteration":158,"passed_time":4.751847859,"remaining_time":25.13398773},
{"learn":[0.1859123935],"iteration":159,"passed_time":4.778040176,"remaining_time":25.08471092},
{"learn":[0.185821007],"iteration":160,"passed_time":4.804923327,"remaining_time":25.03932094},
{"learn":[0.1855219434],"iteration":161,"passed_time":4.835618801,"remaining_time":25.01387997},
{"learn":[0.1853641874],"iteration":162,"passed_time":4.866846362,"remaining_time":24.99110678},
{"learn":[0.1852250232],"iteration":163,"passed_time":4.899855025,"remaining_time":24.97730976},
{"learn":[0.1850785361],"iteration":164,"passed_time":4.932269551,"remaining_time":24.96027318},
{"learn":[0.1850054485],"iteration":165,"passed_time":4.959095387,"remaining_time":24.91497321},
{"learn":[0.1849548482],"iteration":166,"passed_time":4.988709,"remaining_time":24.88379998},
{"learn":[0.1848932332],"iteration":167,"passed_time":5.019690919,"remaining_time":24.85942169},
{"learn":[0.1847759909],"iteration":168,"passed_time":5.050944822,"remaining_time":24.83630264},
{"learn":[0.1846998435],"iteration":169,"passed_time":5.081115982,"remaining_time":24.80780156},
{"learn":[0.1846231757],"iteration":170,"passed_time":5.116637858,"remaining_time":24.80522096},
{"learn":[0.1845721673],"iteration":171,"passed_time":5.150347773,"remaining_time":24.79353463},
{"learn":[0.1845006208],"iteration":172,"passed_time":5.180597926,"remaining_time":24.76505483},
{"learn":[0.184372012],"iteration":173,"passed_time":5.212388855,"remaining_time":24.74386893},
{"learn":[0.1842837466],"iteration":174,"passed_time":5.244008298,"remaining_time":24.7217534},
{"learn":[0.1842512774],"iteration":175,"passed_time":5.277064817,"remaining_time":24.706258},
{"learn":[0.1842037438],"iteration":176,"passed_time":5.309137688,"remaining_time":24.68599049},
{"learn":[0.1839640406],"iteration":177,"passed_time":5.343200653,"remaining_time":24.67478055},
{"learn":[0.1838889287],"iteration":178,"passed_time":5.369281984,"remaining_time":24.62670675},
{"learn":[0.1837526164],"iteration":179,"passed_time":5.399713615,"remaining_time":24.59869536},
{"learn":[0.1836613926],"iteration":180,"passed_time":5.435148392,"remaining_time":24.59329576},
{"learn":[0.1834775869],"iteration":181,"passed_time":5.46801373,"remaining_time":24.57601775},
{"learn":[0.1833247951],"iteration":182,"passed_time":5.497004918,"remaining_time":24.54127332},
{"learn":[0.1832445931],"iteration":183,"passed_time":5.525716622,"remaining_time":24.50535198},
{"learn":[0.1831349209],"iteration":184,"passed_time":5.553456373,"remaining_time":24.46522673},
{"learn":[0.1830347872],"iteration":185,"passed_time":5.582531528,"remaining_time":24.43107884},
{"learn":[0.1829596431],"iteration":186,"passed_time":5.61290836,"remaining_time":24.40264437},
{"learn":[0.1828212919],"iteration":187,"passed_time":5.645261556,"remaining_time":24.38272545},
{"learn":[0.1827598272],"iteration":188,"passed_time":5.677801932,"remaining_time":24.36347813},
{"learn":[0.1826788506],"iteration":189,"passed_time":5.707418125,"remaining_time":24.33162464},
{"learn":[0.1826465982],"iteration":190,"passed_time":5.736047693,"remaining_time":24.29561562},
{"learn":[0.1826201063],"iteration":191,"passed_time":5.76362913,"remaining_time":24.25527259},
{"learn":[0.182582913],"iteration":192,"passed_time":5.801126665,"remaining_time":24.25652445},
{"learn":[0.1825025438],"iteration":193,"passed_time":5.831087433,"remaining_time":24.22606428},
{"learn":[0.1823628233],"iteration":194,"passed_time":5.861330799,"remaining_time":24.19677586},
{"learn":[0.1822853543],"iteration":195,"passed_time":5.892444042,"remaining_time":24.17104597},
{"learn":[0.1822102868],"iteration":196,"passed_time":5.922729356,"remaining_time":24.14188666},
{"learn":[0.1821547537],"iteration":197,"passed_time":5.953413687,"remaining_time":24.11433221},
{"learn":[0.18207482],"iteration":198,"passed_time":5.983193206,"remaining_time":24.08310431},
{"learn":[0.1820299867],"iteration":199,"passed_time":6.011833467,"remaining_time":24.04733387},
{"learn":[0.1819781629],"iteration":200,"passed_time":6.040826748,"remaining_time":24.01303767},
{"learn":[0.1816901626],"iteration":201,"passed_time":6.07048097,"remaining_time":23.98140502},
{"learn":[0.1815080669],"iteration":202,"passed_time":6.10419412,"remaining_time":23.96572765},
{"learn":[0.1814709697],"iteration":203,"passed_time":6.134658649,"remaining_time":23.93719747},
{"learn":[0.1814149855],"iteration":204,"passed_time":6.162886013,"remaining_time":23.89997259},
{"learn":[0.1813170418],"iteration":205,"passed_time":6.196111675,"remaining_time":23.88210034},
{"learn":[0.1812399165],"iteration":206,"passed_time":6.231482929,"remaining_time":23.87229934},
{"learn":[0.1811611386],"iteration":207,"passed_time":6.267037485,"remaining_time":23.86295043},
{"learn":[0.1811197904],"iteration":208,"passed_time":6.298354889,"remaining_time":23.83731443},
{"learn":[0.1809363236],"iteration":209,"passed_time":6.33038943,"remaining_time":23.81432214},
{"learn":[0.1808343744],"iteration":210,"passed_time":6.357030497,"remaining_time":23.77107612},
{"learn":[0.1807811364],"iteration":211,"passed_time":6.386255201,"remaining_time":23.73759009},
{"learn":[0.1805595456],"iteration":212,"passed_time":6.420721266,"remaining_time":23.72351003},
{"learn":[0.1804737405],"iteration":213,"passed_time":6.447793671,"remaining_time":23.6820833},
{"learn":[0.1804427346],"iteration":214,"passed_time":6.478731246,"remaining_time":23.65490246},
{"learn":[0.1804203666],"iteration":215,"passed_time":6.515918436,"remaining_time":23.65037062},
{"learn":[0.1802378655],"iteration":216,"passed_time":6.549162419,"remaining_time":23.63130956},
{"learn":[0.1800316807],"iteration":217,"passed_time":6.580500444,"remaining_time":23.60528141},
{"learn":[0.1798771957],"iteration":218,"passed_time":6.609148594,"remaining_time":23.56961211},
{"learn":[0.179841777],"iteration":219,"passed_time":6.637599191,"remaining_time":23.53330622},
{"learn":[0.1798079967],"iteration":220,"passed_time":6.66532844,"remaining_time":23.49452875},
{"learn":[0.1797610513],"iteration":221,"passed_time":6.696701665,"remaining_time":23.46862115},
{"learn":[0.1797077899],"iteration":222,"passed_time":6.729876503,"remaining_time":23.4489419},
{"learn":[0.1796235386],"iteration":223,"passed_time":6.75958496,"remaining_time":23.41713361},
{"learn":[0.1794316761],"iteration":224,"passed_time":6.788591054,"remaining_time":23.38292474},
{"learn":[0.179357753],"iteration":225,"passed_time":6.821047704,"remaining_time":23.36057931},
{"learn":[0.1792547161],"iteration":226,"passed_time":6.854340162,"remaining_time":23.34099095},
{"learn":[0.1790920896],"iteration":227,"passed_time":6.889208838,"remaining_time":23.3266194},
{"learn":[0.1790630725],"iteration":228,"passed_time":6.915025037,"remaining_time":23.28159085},
{"learn":[0.1790022543],"iteration":229,"passed_time":6.948024347,"remaining_time":23.26077716},
{"learn":[0.1788256511],"iteration":230,"passed_time":6.975625581,"remaining_time":23.22188776},
{"learn":[0.1786750473],"iteration":231,"passed_time":7.008619839,"remaining_time":23.20094843},
{"learn":[0.1786038107],"iteration":232,"passed_time":7.04144203,"remaining_time":23.17933922},
{"learn":[0.1785665978],"iteration":233,"passed_time":7.069449002,"remaining_time":23.14187152},
{"learn":[0.1784451858],"iteration":234,"passed_time":7.106750923,"remaining_time":23.13474237},
{"learn":[0.1783942567],"iteration":235,"passed_time":7.140240209,"remaining_time":23.11501491},
{"learn":[0.1783417075],"iteration":236,"passed_time":7.176153005,"remaining_time":23.1029736},
{"learn":[0.1782869612],"iteration":237,"passed_time":7.210641098,"remaining_time":23.08617024},
{"learn":[0.1782186914],"iteration":238,"passed_time":7.24787305,"remaining_time":23.07795561},
{"learn":[0.1781532507],"iteration":239,"passed_time":7.285454526,"remaining_time":23.070606},
{"learn":[0.1781171015],"iteration":240,"passed_time":7.320179201,"remaining_time":23.05400836},
{"learn":[0.1779839307],"iteration":241,"passed_time":7.348348229,"remaining_time":23.0167271},
{"learn":[0.1778561065],"iteration":242,"passed_time":7.381662306,"remaining_time":22.99554883},
{"learn":[0.1778265649],"iteration":243,"passed_time":7.411859062,"remaining_time":22.9646125},
{"learn":[0.1776869993],"iteration":244,"passed_time":7.440624045,"remaining_time":22.92927001},
{"learn":[0.1775999027],"iteration":245,"passed_time":7.472481326,"remaining_time":22.90345902},
{"learn":[0.1775720217],"iteration":246,"passed_time":7.503402386,"remaining_time":22.87474492},
{"learn":[0.1774116676],"iteration":247,"passed_time":7.534900198,"remaining_time":22.84776189},
{"learn":[0.1773763904],"iteration":248,"passed_time":7.563382918,"remaining_time":22.81164888},
{"learn":[0.1773021578],"iteration":249,"passed_time":7.594572612,"remaining_time":22.78371784},
{"learn":[0.1771368792],"iteration":250,"passed_time":7.627715135,"remaining_time":22.76158819},
{"learn":[0.1770684001],"iteration":251,"passed_time":7.659278008,"remaining_time":22.73468234},
{"learn":[0.1769963507],"iteration":252,"passed_time":7.693174711,"remaining_time":22.71463047},
{"learn":[0.176928025],"iteration":253,"passed_time":7.72159482,"remaining_time":22.67838479},
{"learn":[0.1768519172],"iteration":254,"passed_time":7.747668323,"remaining_time":22.63534471},
{"learn":[0.1767851449],"iteration":255,"passed_time":7.777369131,"remaining_time":22.60297904},
{"learn":[0.1766536941],"iteration":256,"passed_time":7.805612738,"remaining_time":22.56642126},
{"learn":[0.1765908088],"iteration":257,"passed_time":7.835919099,"remaining_time":22.53586035},
{"learn":[0.1764777397],"iteration":258,"passed_time":7.865589801,"remaining_time":22.50348279},
{"learn":[0.176355853],"iteration":259,"passed_time":7.896826458,"remaining_time":22.475583},
{"learn":[0.1763273627],"iteration":260,"passed_time":7.922859479,"remaining_time":22.43292396},
{"learn":[0.1762953581],"iteration":261,"passed_time":7.951009005,"remaining_time":22.39635361},
{"learn":[0.176221553],"iteration":262,"passed_time":7.978974524,"remaining_time":22.35933165},
{"learn":[0.1761144041],"iteration":263,"passed_time":8.01355711,"remaining_time":22.34082588},
{"learn":[0.1760914701],"iteration":264,"passed_time":8.041963186,"remaining_time":22.3050677},
{"learn":[0.1759593259],"iteration":265,"passed_time":8.070458884,"remaining_time":22.26961211},
{"learn":[0.1759056015],"iteration":266,"passed_time":8.100091832,"remaining_time":22.23733076},
{"learn":[0.1758643862],"iteration":267,"passed_time":8.128954208,"remaining_time":22.20296448},
{"learn":[0.175837676],"iteration":268,"passed_time":8.15335284,"remaining_time":22.15650902},
{"learn":[0.1757956314],"iteration":269,"passed_time":8.179115727,"remaining_time":22.11390548},
{"learn":[0.1756559361],"iteration":270,"passed_time":8.2077412,"remaining_time":22.0791267},
{"learn":[0.175541549],"iteration":271,"passed_time":8.240282721,"remaining_time":22.05487434},
{"learn":[0.17547392],"iteration":272,"passed_time":8.268611509,"remaining_time":22.01934274},
{"learn":[0.1754502811],"iteration":273,"passed_time":8.290915881,"remaining_time":21.9679012},
{"learn":[0.1753459789],"iteration":274,"passed_time":8.326104534,"remaining_time":21.95063923},
{"learn":[0.1753147688],"iteration":275,"passed_time":8.357525659,"remaining_time":21.92336441},
{"learn":[0.1752827356],"iteration":276,"passed_time":8.388303539,"remaining_time":21.89438072},
{"learn":[0.1752104689],"iteration":277,"passed_time":8.419424831,"remaining_time":21.866276},
{"learn":[0.1751311216],"iteration":278,"passed_time":8.449149704,"remaining_time":21.83454099},
{"learn":[0.1750620076],"iteration":279,"passed_time":8.479624478,"remaining_time":21.80474866},
{"learn":[0.1749622678],"iteration":280,"passed_time":8.505566353,"remaining_time":21.76335305},
{"learn":[0.1748402589],"iteration":281,"passed_time":8.535678209,"remaining_time":21.73268423},
{"learn":[0.1746742526],"iteration":282,"passed_time":8.566344707,"remaining_time":21.70342458},
{"learn":[0.174597953],"iteration":283,"passed_time":8.597427841,"remaining_time":21.6752054},
{"learn":[0.1744565236],"iteration":284,"passed_time":8.62859444,"remaining_time":21.64717553},
{"learn":[0.1744131731],"iteration":285,"passed_time":8.659261249,"remaining_time":21.61787599},
{"learn":[0.174357886],"iteration":286,"passed_time":8.689390406,"remaining_time":21.58723122},
{"learn":[0.1742474354],"iteration":287,"passed_time":8.717086636,"remaining_time":21.55057529},
{"learn":[0.1742232541],"iteration":288,"passed_time":8.748108147,"remaining_time":21.52216226},
{"learn":[0.1741437685],"iteration":289,"passed_time":8.77731186,"remaining_time":21.48928076},
{"learn":[0.1740416336],"iteration":290,"passed_time":8.811513988,"remaining_time":21.46860281},
{"learn":[0.174000523],"iteration":291,"passed_time":8.840959176,"remaining_time":21.43629828},
{"learn":[0.1738974662],"iteration":292,"passed_time":8.872752783,"remaining_time":21.40967992},
{"learn":[0.1737576361],"iteration":293,"passed_time":8.895736519,"remaining_time":21.36187069},
{"learn":[0.1736533254],"iteration":294,"passed_time":8.924970898,"remaining_time":21.32916774},
{"learn":[0.1735443228],"iteration":295,"passed_time":8.958218104,"remaining_time":21.30603225},
{"learn":[0.1734612293],"iteration":296,"passed_time":8.99298685,"remaining_time":21.28643015},
{"learn":[0.1733544933],"iteration":297,"passed_time":9.033690779,"remaining_time":21.28070781},
{"learn":[0.1732953981],"iteration":298,"passed_time":9.065118951,"remaining_time":21.25300463},
{"learn":[0.1732346867],"iteration":299,"passed_time":9.099638486,"remaining_time":21.2324898},
{"learn":[0.1731308237],"iteration":300,"passed_time":9.130788403,"remaining_time":21.20405679},
{"learn":[0.1730422159],"iteration":301,"passed_time":9.161736537,"remaining_time":21.17513941},
{"learn":[0.1729516327],"iteration":302,"passed_time":9.21723523,"remaining_time":21.20268302},
{"learn":[0.1728548675],"iteration":303,"passed_time":9.258429928,"remaining_time":21.19693168},
{"learn":[0.1728124553],"iteration":304,"passed_time":9.290588139,"remaining_time":21.17035658},
{"learn":[0.1727854716],"iteration":305,"passed_time":9.324627882,"remaining_time":21.14801226},
{"learn":[0.1726350277],"iteration":306,"passed_time":9.359460969,"remaining_time":21.12738258},
{"learn":[0.1726194965],"iteration":307,"passed_time":9.394398827,"remaining_time":21.10689607},
{"learn":[0.1725378152],"iteration":308,"passed_time":9.431922268,"remaining_time":21.09209802},
{"learn":[0.1724939392],"iteration":309,"passed_time":9.473247656,"remaining_time":21.08561575},
{"learn":[0.1724817103],"iteration":310,"passed_time":9.504702513,"remaining_time":21.0570419},
{"learn":[0.1724128763],"iteration":311,"passed_time":9.537304306,"remaining_time":21.03097873},
{"learn":[0.1723893653],"iteration":312,"passed_time":9.56674194,"remaining_time":20.9979288},
{"learn":[0.1723039873],"iteration":313,"passed_time":9.603042953,"remaining_time":20.97989639},
{"learn":[0.1722475291],"iteration":314,"passed_time":9.631782144,"remaining_time":20.94530403},
{"learn":[0.1722066039],"iteration":315,"passed_time":9.662474938,"remaining_time":20.9149774},
{"learn":[0.1721559759],"iteration":316,"passed_time":9.694574532,"remaining_time":20.88767951},
{"learn":[0.1721004631],"iteration":317,"passed_time":9.726414628,"remaining_time":20.85979489},
{"learn":[0.1719093971],"iteration":318,"passed_time":9.758747881,"remaining_time":20.83293827},
{"learn":[0.1718636062],"iteration":319,"passed_time":9.792888153,"remaining_time":20.80988733},
{"learn":[0.1718086979],"iteration":320,"passed_time":9.823194213,"remaining_time":20.77865692},
{"learn":[0.1717249029],"iteration":321,"passed_time":9.854270792,"remaining_time":20.74905465},
{"learn":[0.1716162312],"iteration":322,"passed_time":9.883903611,"remaining_time":20.71641717},
{"learn":[0.1715976699],"iteration":323,"passed_time":9.911376778,"remaining_time":20.67929229},
{"learn":[0.1715464894],"iteration":324,"passed_time":9.941809343,"remaining_time":20.64837325},
{"learn":[0.1715067631],"iteration":325,"passed_time":9.971353007,"remaining_time":20.61561941},
{"learn":[0.1713433425],"iteration":326,"passed_time":10.00422187,"remaining_time":20.5897288},
{"learn":[0.1712225738],"iteration":327,"passed_time":10.03499002,"remaining_time":20.55949174},
{"learn":[0.171186184],"iteration":328,"passed_time":10.06643241,"remaining_time":20.53062658},
{"learn":[0.1710475233],"iteration":329,"passed_time":10.09668149,"remaining_time":20.49932303},
{"learn":[0.1709646938],"iteration":330,"passed_time":10.12832728,"remaining_time":20.47084879},
{"learn":[0.1709071111],"iteration":331,"passed_time":10.16029401,"remaining_time":20.44300121},
{"learn":[0.1708319278],"iteration":332,"passed_time":10.19097085,"remaining_time":20.41254522},
{"learn":[0.1707703047],"iteration":333,"passed_time":10.22089629,"remaining_time":20.3805896},
{"learn":[0.1707397064],"iteration":334,"passed_time":10.24842402,"remaining_time":20.34388648},
{"learn":[0.1706393546],"iteration":335,"passed_time":10.27972737,"remaining_time":20.31469932},
{"learn":[0.1706210151],"iteration":336,"passed_time":10.30684625,"remaining_time":20.27726724},
{"learn":[0.1705546457],"iteration":337,"passed_time":10.33892847,"remaining_time":20.2496173},
{"learn":[0.1705042085],"iteration":338,"passed_time":10.36849656,"remaining_time":20.21703902},
{"learn":[0.1704545567],"iteration":339,"passed_time":10.39667265,"remaining_time":20.18177632},
{"learn":[0.1703570454],"iteration":340,"passed_time":10.42369652,"remaining_time":20.14432847},
{"learn":[0.1703034995],"iteration":341,"passed_time":10.45437668,"remaining_time":20.11397618},
{"learn":[0.170265028],"iteration":342,"passed_time":10.48607721,"remaining_time":20.08557647},
{"learn":[0.1701487468],"iteration":343,"passed_time":10.52173184,"remaining_time":20.06469793},
{"learn":[0.1700808563],"iteration":344,"passed_time":10.55388735,"remaining_time":20.03709048},
{"learn":[0.1699877094],"iteration":345,"passed_time":10.59040592,"remaining_time":20.01770367},
{"learn":[0.1699301205],"iteration":346,"passed_time":10.62589453,"remaining_time":19.99627991},
{"learn":[0.1699184088],"iteration":347,"passed_time":10.65959182,"remaining_time":19.97141916},
{"learn":[0.1698786691],"iteration":348,"passed_time":10.69361877,"remaining_time":19.94712269},
{"learn":[0.1698435392],"iteration":349,"passed_time":10.72399554,"remaining_time":19.91599172},
{"learn":[0.1698056467],"iteration":350,"passed_time":10.75549301,"remaining_time":19.88693722},
{"learn":[0.1697534317],"iteration":351,"passed_time":10.7894517,"remaining_time":19.86239972},
{"learn":[0.1697366415],"iteration":352,"passed_time":10.82051458,"remaining_time":19.83250123},
{"learn":[0.1696577541],"iteration":353,"passed_time":10.8513668,"remaining_time":19.80221174},
{"learn":[0.1695593274],"iteration":354,"passed_time":10.88201856,"remaining_time":19.77155484},
{"learn":[0.1695055272],"iteration":355,"passed_time":10.91409192,"remaining_time":19.74346965},
{"learn":[0.1694214679],"iteration":356,"passed_time":10.94691814,"remaining_time":19.7167181},
{"learn":[0.1693096821],"iteration":357,"passed_time":10.97947873,"remaining_time":19.68945627},
{"learn":[0.1692808066],"iteration":358,"passed_time":11.01016204,"remaining_time":19.658813},
{"learn":[0.1691728384],"iteration":359,"passed_time":11.04787836,"remaining_time":19.64067265},
{"learn":[0.1691198673],"iteration":360,"passed_time":11.07761074,"remaining_time":19.60829159},
{"learn":[0.1690355361],"iteration":361,"passed_time":11.11056796,"remaining_time":19.58160873},
{"learn":[0.1690106387],"iteration":362,"passed_time":11.13763647,"remaining_time":19.54455766},
{"learn":[0.1689971028],"iteration":363,"passed_time":11.16904849,"remaining_time":19.51515067},
{"learn":[0.1689440599],"iteration":364,"passed_time":11.20314015,"remaining_time":19.49039452},
{"learn":[0.1688964081],"iteration":365,"passed_time":11.23419963,"remaining_time":19.46033488},
{"learn":[0.1688642344],"iteration":366,"passed_time":11.26264359,"remaining_time":19.42575857},
{"learn":[0.1687726537],"iteration":367,"passed_time":11.29351551,"remaining_time":19.39538533},
{"learn":[0.1687169459],"iteration":368,"passed_time":11.32442758,"remaining_time":19.36507805},
{"learn":[0.168664093],"iteration":369,"passed_time":11.35382029,"remaining_time":19.33218049},
{"learn":[0.1685992356],"iteration":370,"passed_time":11.38099271,"remaining_time":19.29553751},
{"learn":[0.1685595869],"iteration":371,"passed_time":11.41431883,"remaining_time":19.26933394},
{"learn":[0.1684161799],"iteration":372,"passed_time":11.4468049,"remaining_time":19.24168008},
{"learn":[0.1683407403],"iteration":373,"passed_time":11.47927407,"remaining_time":19.2139721},
{"learn":[0.1682879238],"iteration":374,"passed_time":11.51380843,"remaining_time":19.18968072},
{"learn":[0.1682030811],"iteration":375,"passed_time":11.54676203,"remaining_time":19.16271146},
{"learn":[0.1681767236],"iteration":376,"passed_time":11.57867089,"remaining_time":19.13398399},
{"learn":[0.1681518245],"iteration":377,"passed_time":11.61024247,"remaining_time":19.10468471},
{"learn":[0.1680989891],"iteration":378,"passed_time":11.64205667,"remaining_time":19.07577096},
{"learn":[0.168040169],"iteration":379,"passed_time":11.66850366,"remaining_time":19.03808492},
{"learn":[0.1680065941],"iteration":380,"passed_time":11.69992097,"remaining_time":19.00853301},
{"learn":[0.1679089988],"iteration":381,"passed_time":11.73194501,"remaining_time":18.97995293},
{"learn":[0.1678304077],"iteration":382,"passed_time":11.76352848,"remaining_time":18.95064509},
{"learn":[0.167796044],"iteration":383,"passed_time":11.79101633,"remaining_time":18.91475536},
{"learn":[0.1677020759],"iteration":384,"passed_time":11.82493876,"remaining_time":18.88918789},
{"learn":[0.167656187],"iteration":385,"passed_time":11.85524411,"remaining_time":18.85782354},
{"learn":[0.1676182907],"iteration":386,"passed_time":11.88523797,"remaining_time":18.82597125},
{"learn":[0.1675945181],"iteration":387,"passed_time":11.91598417,"remaining_time":18.79531523},
{"learn":[0.1675648405],"iteration":388,"passed_time":11.94477285,"remaining_time":18.7615841},
{"learn":[0.1675247876],"iteration":389,"passed_time":11.97526761,"remaining_time":18.73054678},
{"learn":[0.1674882516],"iteration":390,"passed_time":12.00560424,"remaining_time":18.69926594},
{"learn":[0.1674126257],"iteration":391,"passed_time":12.03774505,"remaining_time":18.67078824},
{"learn":[0.1673352425],"iteration":392,"passed_time":12.07134809,"remaining_time":18.64455036},
{"learn":[0.1673320102],"iteration":393,"passed_time":12.10273707,"remaining_time":18.61486971},
{"learn":[0.1672691167],"iteration":394,"passed_time":12.13456013,"remaining_time":18.58584526},
{"learn":[0.1672484026],"iteration":395,"passed_time":12.16164213,"remaining_time":18.54957537},
{"learn":[0.1671938568],"iteration":396,"passed_time":12.19363385,"remaining_time":18.5208091},
{"learn":[0.1671509463],"iteration":397,"passed_time":12.22208241,"remaining_time":18.48666737},
{"learn":[0.1671455707],"iteration":398,"passed_time":12.24613084,"remaining_time":18.4459264},
{"learn":[0.1669652403],"iteration":399,"passed_time":12.27793389,"remaining_time":18.41690084},
{"learn":[0.1668655371],"iteration":400,"passed_time":12.33907052,"remaining_time":18.43167891},
{"learn":[0.1667319657],"iteration":401,"passed_time":12.38327698,"remaining_time":18.4208946},
{"learn":[0.1665371532],"iteration":402,"passed_time":12.41122877,"remaining_time":18.38586495},
{"learn":[0.1664895482],"iteration":403,"passed_time":12.43932178,"remaining_time":18.35107867},
{"learn":[0.1663886188],"iteration":404,"passed_time":12.47232249,"remaining_time":18.32353551},
{"learn":[0.1663509321],"iteration":405,"passed_time":12.5032526,"remaining_time":18.29293607},
{"learn":[0.1663007578],"iteration":406,"passed_time":12.53204589,"remaining_time":18.25922165},
{"learn":[0.166273777],"iteration":407,"passed_time":12.56294418,"remaining_time":18.22858567},
{"learn":[0.1661840214],"iteration":408,"passed_time":12.59466148,"remaining_time":18.19913187},
{"learn":[0.1661440023],"iteration":409,"passed_time":12.62635332,"remaining_time":18.16963038},
{"learn":[0.1660229773],"iteration":410,"passed_time":12.65623588,"remaining_time":18.13752539},
{"learn":[0.1659182347],"iteration":411,"passed_time":12.68191308,"remaining_time":18.09942935},
{"learn":[0.1658556358],"iteration":412,"passed_time":12.71242538,"remaining_time":18.06826561},
{"learn":[0.1658057917],"iteration":413,"passed_time":12.74206345,"remaining_time":18.03586759},
{"learn":[0.1657695304],"iteration":414,"passed_time":12.77311228,"remaining_time":18.00547152},
{"learn":[0.1656763103],"iteration":415,"passed_time":12.80547848,"remaining_time":17.97692171},
{"learn":[0.1656461334],"iteration":416,"passed_time":12.83763639,"remaining_time":17.94806238},
{"learn":[0.1656104118],"iteration":417,"passed_time":12.87132636,"remaining_time":17.92132043},
{"learn":[0.1655833787],"iteration":418,"passed_time":12.91089875,"remaining_time":17.90270208},
{"learn":[0.1654878607],"iteration":419,"passed_time":12.94731421,"remaining_time":17.87962439},
{"learn":[0.1654872534],"iteration":420,"passed_time":12.96925615,"remaining_time":17.83657793},
{"learn":[0.1654787951],"iteration":421,"passed_time":13.00647478,"remaining_time":17.8145555},
{"learn":[0.1654568929],"iteration":422,"passed_time":13.03635884,"remaining_time":17.78245638},
{"learn":[0.1654049868],"iteration":423,"passed_time":13.07220714,"remaining_time":17.75847008},
{"learn":[0.1653563585],"iteration":424,"passed_time":13.10596001,"remaining_time":17.73159295},
{"learn":[0.1653147346],"iteration":425,"passed_time":13.14025628,"remaining_time":17.70541574},
{"learn":[0.1652968509],"iteration":426,"passed_time":13.17023339,"remaining_time":17.67340452},
{"learn":[0.1652072597],"iteration":427,"passed_time":13.20417118,"remaining_time":17.64669606},
{"learn":[0.1651566059],"iteration":428,"passed_time":13.23863866,"remaining_time":17.62065891},
{"learn":[0.1651085944],"iteration":429,"passed_time":13.27149817,"remaining_time":17.59245106},
{"learn":[0.1650431027],"iteration":430,"passed_time":13.30379476,"remaining_time":17.56347846},
{"learn":[0.1650322859],"iteration":431,"passed_time":13.33713821,"remaining_time":17.5358669},
{"learn":[0.1649903345],"iteration":432,"passed_time":13.36824155,"remaining_time":17.50529551},
{"learn":[0.1649236299],"iteration":433,"passed_time":13.3982059,"remaining_time":17.47323627},
{"learn":[0.1649113129],"iteration":434,"passed_time":13.42791174,"remaining_time":17.44085088},
{"learn":[0.16487445],"iteration":435,"passed_time":13.45983716,"remaining_time":17.41134898},
{"learn":[0.1647900995],"iteration":436,"passed_time":13.49174895,"remaining_time":17.38181844},
{"learn":[0.1646719736],"iteration":437,"passed_time":13.52115241,"remaining_time":17.34905858},
{"learn":[0.1646545879],"iteration":438,"passed_time":13.55247826,"remaining_time":17.31877063},
{"learn":[0.1645911479],"iteration":439,"passed_time":13.58827274,"remaining_time":17.29416531},
{"learn":[0.16452198],"iteration":440,"passed_time":13.61832224,"remaining_time":17.26222706},
{"learn":[0.1644594068],"iteration":441,"passed_time":13.65000062,"remaining_time":17.23235372},
{"learn":[0.1643894912],"iteration":442,"passed_time":13.69023152,"remaining_time":17.21322564},
{"learn":[0.1643553362],"iteration":443,"passed_time":13.72497265,"remaining_time":17.18712792},
{"learn":[0.1643407852],"iteration":444,"passed_time":13.75198637,"remaining_time":17.15135379},
{"learn":[0.1642743921],"iteration":445,"passed_time":13.78409211,"remaining_time":17.12194401},
{"learn":[0.164233376],"iteration":446,"passed_time":13.8155716,"remaining_time":17.09174742},
{"learn":[0.1642189628],"iteration":447,"passed_time":13.84529151,"remaining_time":17.05937704},
{"learn":[0.1642077447],"iteration":448,"passed_time":13.87194669,"remaining_time":17.02325752},
{"learn":[0.1641684805],"iteration":449,"passed_time":13.90393318,"remaining_time":16.99369611},
{"learn":[0.1641470605],"iteration":450,"passed_time":13.93992294,"remaining_time":16.9689971},
{"learn":[0.1640999193],"iteration":451,"passed_time":13.97455986,"remaining_time":16.94260797},
{"learn":[0.1640836885],"iteration":452,"passed_time":14.00541302,"remaining_time":16.91161352},
{"learn":[0.1640250817],"iteration":453,"passed_time":14.03921817,"remaining_time":16.88416987},
{"learn":[0.163995471],"iteration":454,"passed_time":14.07355488,"remaining_time":16.85733496},
{"learn":[0.1639746062],"iteration":455,"passed_time":14.10925428,"remaining_time":16.83209283},
{"learn":[0.1639110845],"iteration":456,"passed_time":14.15054034,"remaining_time":16.8134429},
{"learn":[0.1638696089],"iteration":457,"passed_time":14.18517339,"remaining_time":16.78682091},
{"learn":[0.1637794661],"iteration":458,"passed_time":14.21402325,"remaining_time":16.75334766},
{"learn":[0.1637297712],"iteration":459,"passed_time":14.24122494,"remaining_time":16.71795972},
{"learn":[0.1636524476],"iteration":460,"passed_time":14.26930566,"remaining_time":16.68363504},
{"learn":[0.1636102375],"iteration":461,"passed_time":14.30478757,"remaining_time":16.65795609},
{"learn":[0.1635585866],"iteration":462,"passed_time":14.33830698,"remaining_time":16.62995864},
{"learn":[0.1635371286],"iteration":463,"passed_time":14.36561313,"remaining_time":16.59476},
{"learn":[0.1634935076],"iteration":464,"passed_time":14.3948823,"remaining_time":16.56185383},
{"learn":[0.1634596809],"iteration":465,"passed_time":14.42465602,"remaining_time":16.52954145},
{"learn":[0.1634213024],"iteration":466,"passed_time":14.45553668,"remaining_time":16.49850332},
{"learn":[0.1634024978],"iteration":467,"passed_time":14.4826864,"remaining_time":16.46322471},
{"learn":[0.1633373462],"iteration":468,"passed_time":14.51656069,"remaining_time":16.4355943},
{"learn":[0.1632588303],"iteration":469,"passed_time":14.54444373,"remaining_time":16.40118122},
{"learn":[0.1632410512],"iteration":470,"passed_time":14.57496607,"remaining_time":16.3697602},
{"learn":[0.1632031782],"iteration":471,"passed_time":14.60541989,"remaining_time":16.33826632},
{"learn":[0.1631522839],"iteration":472,"passed_time":14.63847986,"remaining_time":16.30968052},
{"learn":[0.1631367607],"iteration":473,"passed_time":14.66988924,"remaining_time":16.27924418},
{"learn":[0.163099386],"iteration":474,"passed_time":14.70256164,"remaining_time":16.2501997},
{"learn":[0.1630530685],"iteration":475,"passed_time":14.73403326,"remaining_time":16.21981812},
{"learn":[0.1630470866],"iteration":476,"passed_time":14.76300939,"remaining_time":16.18669583},
{"learn":[0.1629995654],"iteration":477,"passed_time":14.79732423,"remaining_time":16.15942102},
{"learn":[0.1629452916],"iteration":478,"passed_time":14.83397422,"remaining_time":16.13465672},
{"learn":[0.1628940347],"iteration":479,"passed_time":14.86391649,"remaining_time":16.10257619},
{"learn":[0.1628253058],"iteration":480,"passed_time":14.89177254,"remaining_time":16.06825353},
{"learn":[0.1627951835],"iteration":481,"passed_time":14.92536739,"remaining_time":16.04012512},
{"learn":[0.1627603202],"iteration":482,"passed_time":14.95769421,"remaining_time":16.01061678},
{"learn":[0.1627087211],"iteration":483,"passed_time":14.98191485,"remaining_time":15.97245468},
{"learn":[0.162690185],"iteration":484,"passed_time":15.00863001,"remaining_time":15.93699888},
{"learn":[0.1626846403],"iteration":485,"passed_time":15.03628714,"remaining_time":15.90257529},
{"learn":[0.1626717052],"iteration":486,"passed_time":15.06453795,"remaining_time":15.86880487},
{"learn":[0.162614594],"iteration":487,"passed_time":15.09455716,"remaining_time":15.83691243},
{"learn":[0.1625766483],"iteration":488,"passed_time":15.12627514,"remaining_time":15.80680285},
{"learn":[0.1625210646],"iteration":489,"passed_time":15.1607965,"remaining_time":15.77960452},
{"learn":[0.1624882476],"iteration":490,"passed_time":15.19174183,"remaining_time":15.74866923},
{"learn":[0.1624245632],"iteration":491,"passed_time":15.22554511,"remaining_time":15.72068479},
{"learn":[0.1623777237],"iteration":492,"passed_time":15.26240273,"remaining_time":15.69581781},
{"learn":[0.1623602008],"iteration":493,"passed_time":15.30026614,"remaining_time":15.67193252},
{"learn":[0.1623343611],"iteration":494,"passed_time":15.33324196,"remaining_time":15.64300442},
{"learn":[0.1623003379],"iteration":495,"passed_time":15.36810056,"remaining_time":15.61597314},
{"learn":[0.1622442075],"iteration":496,"passed_time":15.40287921,"remaining_time":15.58882946},
{"learn":[0.1622185638],"iteration":497,"passed_time":15.43149036,"remaining_time":15.55543807},
{"learn":[0.162180956],"iteration":498,"passed_time":15.46382676,"remaining_time":15.52580602},
{"learn":[0.1621511123],"iteration":499,"passed_time":15.49465414,"remaining_time":15.49465414},
{"learn":[0.1621373439],"iteration":500,"passed_time":15.52399734,"remaining_time":15.46202529},
{"learn":[0.1620982801],"iteration":501,"passed_time":15.55469621,"remaining_time":15.4307544},
{"learn":[0.1620841294],"iteration":502,"passed_time":15.58349654,"remaining_time":15.3976099},
{"learn":[0.1620425819],"iteration":503,"passed_time":15.61558934,"remaining_time":15.36772284},
{"learn":[0.1619276116],"iteration":504,"passed_time":15.64828205,"remaining_time":15.33841508},
{"learn":[0.1618776314],"iteration":505,"passed_time":15.68096088,"remaining_time":15.30908039},
{"learn":[0.1618516719],"iteration":506,"passed_time":15.71375089,"remaining_time":15.27984061},
{"learn":[0.1618327599],"iteration":507,"passed_time":15.74231197,"remaining_time":15.24649112},
{"learn":[0.1618011106],"iteration":508,"passed_time":15.76992601,"remaining_time":15.2122469},
{"learn":[0.1617178453],"iteration":509,"passed_time":15.80299462,"remaining_time":15.18326935},
{"learn":[0.1616864129],"iteration":510,"passed_time":15.83362021,"remaining_time":15.15193793},
{"learn":[0.1616720726],"iteration":511,"passed_time":15.86017059,"remaining_time":15.11672509},
{"learn":[0.1616316904],"iteration":512,"passed_time":15.8952642,"remaining_time":15.08965627},
{"learn":[0.1616053835],"iteration":513,"passed_time":15.92485836,"remaining_time":15.05735635},
{"learn":[0.1615669715],"iteration":514,"passed_time":15.95479231,"remaining_time":15.02538693},
{"learn":[0.1615385267],"iteration":515,"passed_time":15.98111528,"remaining_time":14.99003836},
{"learn":[0.1614872776],"iteration":516,"passed_time":16.00927663,"remaining_time":14.95644219},
{"learn":[0.1613538978],"iteration":517,"passed_time":16.03893849,"remaining_time":14.92426323},
{"learn":[0.1613059554],"iteration":518,"passed_time":16.0692388,"remaining_time":14.89268567},
{"learn":[0.1612686612],"iteration":519,"passed_time":16.11447597,"remaining_time":14.8749009},
{"learn":[0.1612440519],"iteration":520,"passed_time":16.14387424,"remaining_time":14.84244868},
{"learn":[0.1610676875],"iteration":521,"passed_time":16.16926597,"remaining_time":14.80633933},
{"learn":[0.1610314511],"iteration":522,"passed_time":16.1961158,"remaining_time":14.77160083},
{"learn":[0.1610050216],"iteration":523,"passed_time":16.2240899,"remaining_time":14.73791373},
{"learn":[0.1609717862],"iteration":524,"passed_time":16.25358666,"remaining_time":14.70562602},
{"learn":[0.1609327359],"iteration":525,"passed_time":16.28615419,"remaining_time":14.67611613},
{"learn":[0.1608972836],"iteration":526,"passed_time":16.32980673,"remaining_time":14.65654381},
{"learn":[0.1608739313],"iteration":527,"passed_time":16.36619639,"remaining_time":14.63038768},
{"learn":[0.1607990129],"iteration":528,"passed_time":16.39877507,"remaining_time":14.60079973},
{"learn":[0.1607576674],"iteration":529,"passed_time":16.42858293,"remaining_time":14.56874336},
{"learn":[0.1606801399],"iteration":530,"passed_time":16.45806333,"remaining_time":14.53640622},
{"learn":[0.1606501576],"iteration":531,"passed_time":16.49212319,"remaining_time":14.50810837},
{"learn":[0.1606158546],"iteration":532,"passed_time":16.53530863,"remaining_time":14.48778448},
{"learn":[0.1606032894],"iteration":533,"passed_time":16.56802422,"remaining_time":14.45823836},
{"learn":[0.1605357372],"iteration":534,"passed_time":16.60539905,"remaining_time":14.43273002},
{"learn":[0.1604835978],"iteration":535,"passed_time":16.64748992,"remaining_time":14.41125993},
{"learn":[0.1604485584],"iteration":536,"passed_time":16.67738287,"remaining_time":14.37919603},
{"learn":[0.1604304345],"iteration":537,"passed_time":16.70963597,"remaining_time":14.34916695},
{"learn":[0.1604074691],"iteration":538,"passed_time":16.74249155,"remaining_time":14.31964491},
{"learn":[0.1603570603],"iteration":539,"passed_time":16.77927306,"remaining_time":14.29345483},
{"learn":[0.1603070348],"iteration":540,"passed_time":16.81302127,"remaining_time":14.26465206},
{"learn":[0.1602760855],"iteration":541,"passed_time":16.84920185,"remaining_time":14.23788644},
{"learn":[0.160243456],"iteration":542,"passed_time":16.87724523,"remaining_time":14.2042377},
{"learn":[0.1602067992],"iteration":543,"passed_time":16.90997677,"remaining_time":14.17453935},
{"learn":[0.1601472025],"iteration":544,"passed_time":16.94671498,"remaining_time":14.14817489},
{"learn":[0.1601425432],"iteration":545,"passed_time":16.98060919,"remaining_time":14.11940765},
{"learn":[0.1601165587],"iteration":546,"passed_time":17.01100107,"remaining_time":14.08772118},
{"learn":[0.160084091],"iteration":547,"passed_time":17.04735862,"remaining_time":14.06096003},
{"learn":[0.1600696259],"iteration":548,"passed_time":17.08133016,"remaining_time":14.03220383},
{"learn":[0.1600175923],"iteration":549,"passed_time":17.11480107,"remaining_time":14.00301906},
{"learn":[0.1600041944],"iteration":550,"passed_time":17.14971817,"remaining_time":13.9749972},
{"learn":[0.1599924818],"iteration":551,"passed_time":17.18454539,"remaining_time":13.94687742},
{"learn":[0.1599482965],"iteration":552,"passed_time":17.21418116,"remaining_time":13.91453703},
{"learn":[0.1598899683],"iteration":553,"passed_time":17.24683334,"remaining_time":13.88463479},
{"learn":[0.1598598674],"iteration":554,"passed_time":17.28102021,"remaining_time":13.85595314},
{"learn":[0.1598210014],"iteration":555,"passed_time":17.31492719,"remaining_time":13.82702819},
{"learn":[0.1597745644],"iteration":556,"passed_time":17.34509893,"remaining_time":13.79511459},
{"learn":[0.1597274451],"iteration":557,"passed_time":17.38313504,"remaining_time":13.76943672},
{"learn":[0.1597078177],"iteration":558,"passed_time":17.41854536,"remaining_time":13.74164312},
{"learn":[0.1596771742],"iteration":559,"passed_time":17.45294008,"remaining_time":13.71302435},
{"learn":[0.1596217853],"iteration":560,"passed_time":17.48775219,"remaining_time":13.6847116},
{"learn":[0.1595937861],"iteration":561,"passed_time":17.52005305,"remaining_time":13.65441857},
{"learn":[0.1595710902],"iteration":562,"passed_time":17.55530546,"remaining_time":13.62640939},
{"learn":[0.1595345886],"iteration":563,"passed_time":17.5923181,"remaining_time":13.59973527},
{"learn":[0.1595087293],"iteration":564,"passed_time":17.62686987,"remaining_time":13.5711299},
{"learn":[0.1594683561],"iteration":565,"passed_time":17.66015229,"remaining_time":13.5415302},
{"learn":[0.1594473746],"iteration":566,"passed_time":17.69464257,"remaining_time":13.51283992},
{"learn":[0.1593773332],"iteration":567,"passed_time":17.72708543,"remaining_time":13.48257201},
{"learn":[0.1593523391],"iteration":568,"passed_time":17.76046189,"remaining_time":13.45300365},
{"learn":[0.1593387218],"iteration":569,"passed_time":17.79336983,"remaining_time":13.42306847},
{"learn":[0.1593064],"iteration":570,"passed_time":17.82336411,"remaining_time":13.3909338},
{"learn":[0.1592549547],"iteration":571,"passed_time":17.85419214,"remaining_time":13.35943048},
{"learn":[0.1591918001],"iteration":572,"passed_time":17.88504694,"remaining_time":13.32794946},
{"learn":[0.1590405027],"iteration":573,"passed_time":17.91777798,"remaining_time":13.2978631},
{"learn":[0.1590074276],"iteration":574,"passed_time":17.95070129,"remaining_time":13.26790965},
{"learn":[0.1589859693],"iteration":575,"passed_time":17.98079597,"remaining_time":13.2358637},
{"learn":[0.1588985176],"iteration":576,"passed_time":18.00957638,"remaining_time":13.20286102},
{"learn":[0.1588732107],"iteration":577,"passed_time":18.03698007,"remaining_time":13.1688678},
{"learn":[0.1587262514],"iteration":578,"passed_time":18.0654837,"remaining_time":13.13569713},
{"learn":[0.1586503382],"iteration":579,"passed_time":18.09479067,"remaining_time":13.10312428},
{"learn":[0.1586462148],"iteration":580,"passed_time":18.12375815,"remaining_time":13.07031784},
{"learn":[0.1585983221],"iteration":581,"passed_time":18.15441557,"remaining_time":13.03873833},
{"learn":[0.1585658739],"iteration":582,"passed_time":18.18738488,"remaining_time":13.0088156},
{"learn":[0.1585556667],"iteration":583,"passed_time":18.2171205,"remaining_time":12.97657899},
{"learn":[0.158508717],"iteration":584,"passed_time":18.24814749,"remaining_time":12.94526703},
{"learn":[0.1584268617],"iteration":585,"passed_time":18.28221961,"remaining_time":12.91610737},
{"learn":[0.1583815827],"iteration":586,"passed_time":18.30881395,"remaining_time":12.88166978},
{"learn":[0.1583171622],"iteration":587,"passed_time":18.3413804,"remaining_time":12.85144341},
{"learn":[0.1582377247],"iteration":588,"passed_time":18.37282963,"remaining_time":12.8204295},
{"learn":[0.1581951056],"iteration":589,"passed_time":18.4048891,"remaining_time":12.78983819},
{"learn":[0.1581638532],"iteration":590,"passed_time":18.43691191,"remaining_time":12.75921653},
{"learn":[0.1581245923],"iteration":591,"passed_time":18.46684475,"remaining_time":12.72714976},
{"learn":[0.1580689297],"iteration":592,"passed_time":18.49961895,"remaining_time":12.69704032},
{"learn":[0.1580278756],"iteration":593,"passed_time":18.53523631,"remaining_time":12.66886522},
{"learn":[0.1579615298],"iteration":594,"passed_time":18.56598246,"remaining_time":12.6373494},
{"learn":[0.1579335498],"iteration":595,"passed_time":18.59770925,"remaining_time":12.6065009},
{"learn":[0.1578911183],"iteration":596,"passed_time":18.63011218,"remaining_time":12.57610588},
{"learn":[0.1578190645],"iteration":597,"passed_time":18.66288767,"remaining_time":12.54595459},
{"learn":[0.1577823317],"iteration":598,"passed_time":18.69190523,"remaining_time":12.5132788},
{"learn":[0.157705249],"iteration":599,"passed_time":18.7221772,"remaining_time":12.48145147},
{"learn":[0.1576833343],"iteration":600,"passed_time":18.75366841,"remaining_time":12.45043876},
{"learn":[0.1576603944],"iteration":601,"passed_time":18.78608939,"remaining_time":12.42003916},
{"learn":[0.1576111582],"iteration":602,"passed_time":18.82211728,"remaining_time":12.39200756},
{"learn":[0.1575855234],"iteration":603,"passed_time":18.85428019,"remaining_time":12.36141549},
{"learn":[0.1575432194],"iteration":604,"passed_time":18.8883402,"remaining_time":12.33205682},
{"learn":[0.1575128684],"iteration":605,"passed_time":18.92287723,"remaining_time":12.30299278},
{"learn":[0.1574488399],"iteration":606,"passed_time":18.95405379,"remaining_time":12.27173499},
{"learn":[0.1573799165],"iteration":607,"passed_time":18.98726359,"remaining_time":12.24178837},
{"learn":[0.1573177987],"iteration":608,"passed_time":19.01712524,"remaining_time":12.20968139},
{"learn":[0.1572789045],"iteration":609,"passed_time":19.05016327,"remaining_time":12.17961258},
{"learn":[0.1571965083],"iteration":610,"passed_time":19.08396492,"remaining_time":12.15002022},
{"learn":[0.1571887235],"iteration":611,"passed_time":19.11424009,"remaining_time":12.11817836},
{"learn":[0.157168293],"iteration":612,"passed_time":19.14505594,"remaining_time":12.08668295},
{"learn":[0.1571251382],"iteration":613,"passed_time":19.17752843,"remaining_time":12.05623123},
{"learn":[0.1571113143],"iteration":614,"passed_time":19.20756337,"remaining_time":12.02424699},
{"learn":[0.157069774],"iteration":615,"passed_time":19.2399786,"remaining_time":11.9937529},
{"learn":[0.157032426],"iteration":616,"passed_time":19.27333035,"remaining_time":11.96383391},
{"learn":[0.1569681859],"iteration":617,"passed_time":19.30771636,"remaining_time":11.93454312},
{"learn":[0.1569591611],"iteration":618,"passed_time":19.33664463,"remaining_time":11.90187658},
{"learn":[0.1569407206],"iteration":619,"passed_time":19.37383278,"remaining_time":11.8742846},
{"learn":[0.1569174836],"iteration":620,"passed_time":19.40582955,"remaining_time":11.8434934},
{"learn":[0.15688515],"iteration":621,"passed_time":19.43853807,"remaining_time":11.81313085},
{"learn":[0.1568753854],"iteration":622,"passed_time":19.47245082,"remaining_time":11.7834895},
{"learn":[0.1568265624],"iteration":623,"passed_time":19.51195135,"remaining_time":11.75720146},
{"learn":[0.1568227868],"iteration":624,"passed_time":19.54184673,"remaining_time":11.72510804},
{"learn":[0.1567783499],"iteration":625,"passed_time":19.57546689,"remaining_time":11.69524699},
{"learn":[0.1567331261],"iteration":626,"passed_time":19.60913933,"remaining_time":11.66540505},
{"learn":[0.1566728697],"iteration":627,"passed_time":19.64282403,"remaining_time":11.63555818},
{"learn":[0.1566301169],"iteration":628,"passed_time":19.67088927,"remaining_time":11.60238461},
{"learn":[0.1566105201],"iteration":629,"passed_time":19.70859443,"remaining_time":11.57488879},
{"learn":[0.1565458077],"iteration":630,"passed_time":19.74439946,"remaining_time":11.54624945},
{"learn":[0.1565139683],"iteration":631,"passed_time":19.77212162,"remaining_time":11.51288094},
{"learn":[0.1564683801],"iteration":632,"passed_time":19.80023684,"remaining_time":11.47975817},
{"learn":[0.1564242794],"iteration":633,"passed_time":19.82945113,"remaining_time":11.44728567},
{"learn":[0.1563937216],"iteration":634,"passed_time":19.85943823,"remaining_time":11.41526764},
{"learn":[0.1563830543],"iteration":635,"passed_time":19.88714382,"remaining_time":11.38195024},
{"learn":[0.1563783183],"iteration":636,"passed_time":19.91599124,"remaining_time":11.34930113},
{"learn":[0.1563703349],"iteration":637,"passed_time":19.94463861,"remaining_time":11.31655043},
{"learn":[0.1563209435],"iteration":638,"passed_time":19.97753283,"remaining_time":11.28621182},
{"learn":[0.1562789698],"iteration":639,"passed_time":20.00760881,"remaining_time":11.25427995},
{"learn":[0.156222898],"iteration":640,"passed_time":20.03761226,"remaining_time":11.22231326},
{"learn":[0.1561931781],"iteration":641,"passed_time":20.07132094,"remaining_time":11.19241884},
{"learn":[0.1561660379],"iteration":642,"passed_time":20.10267697,"remaining_time":11.16120634},
{"learn":[0.1561562093],"iteration":643,"passed_time":20.13210202,"remaining_time":11.12892596},
{"learn":[0.1561352995],"iteration":644,"passed_time":20.15977865,"remaining_time":11.09569212},
{"learn":[0.1560771593],"iteration":645,"passed_time":20.18716887,"remaining_time":11.06231854},
{"learn":[0.1560429276],"iteration":646,"passed_time":20.21141432,"remaining_time":11.02724769},
{"learn":[0.156017658],"iteration":647,"passed_time":20.24115948,"remaining_time":10.99519774},
{"learn":[0.1559733986],"iteration":648,"passed_time":20.27276262,"remaining_time":10.96415975},
{"learn":[0.1559559642],"iteration":649,"passed_time":20.30302731,"remaining_time":10.93239932},
{"learn":[0.1559165203],"iteration":650,"passed_time":20.33296922,"remaining_time":10.90047044},
{"learn":[0.1558618465],"iteration":651,"passed_time":20.36045058,"remaining_time":10.86723436},
{"learn":[0.1558242779],"iteration":652,"passed_time":20.39068074,"remaining_time":10.83547659},
{"learn":[0.1557777123],"iteration":653,"passed_time":20.42019502,"remaining_time":10.80334476},
{"learn":[0.1557739738],"iteration":654,"passed_time":20.45109341,"remaining_time":10.77194996},
{"learn":[0.1557422992],"iteration":655,"passed_time":20.5251312,"remaining_time":10.76317856},
{"learn":[0.155725316],"iteration":656,"passed_time":20.55823721,"remaining_time":10.73283921},
{"learn":[0.1556858063],"iteration":657,"passed_time":20.59520485,"remaining_time":10.70449857},
{"learn":[0.155662327],"iteration":658,"passed_time":20.63341592,"remaining_time":10.67677516},
{"learn":[0.1556243974],"iteration":659,"passed_time":20.67007549,"remaining_time":10.64822071},
{"learn":[0.155596065],"iteration":660,"passed_time":20.70784395,"remaining_time":10.62021044},
{"learn":[0.1555228996],"iteration":661,"passed_time":20.75423222,"remaining_time":10.59657174},
{"learn":[0.1554962225],"iteration":662,"passed_time":20.79575828,"remaining_time":10.57039297},
{"learn":[0.1554812042],"iteration":663,"passed_time":20.83260105,"remaining_time":10.54179812},
{"learn":[0.1554713709],"iteration":664,"passed_time":20.8629319,"remaining_time":10.50989803},
{"learn":[0.1554394358],"iteration":665,"passed_time":20.89754996,"remaining_time":10.48015268},
{"learn":[0.155376219],"iteration":666,"passed_time":20.93003979,"remaining_time":10.44933021},
{"learn":[0.155328401],"iteration":667,"passed_time":20.96482926,"remaining_time":10.41964568},
{"learn":[0.1552999881],"iteration":668,"passed_time":20.99523663,"remaining_time":10.38777776},
{"learn":[0.1552752822],"iteration":669,"passed_time":21.02713145,"remaining_time":10.35664683},
{"learn":[0.1552107077],"iteration":670,"passed_time":21.06231507,"remaining_time":10.32712617},
{"learn":[0.1551996596],"iteration":671,"passed_time":21.09455837,"remaining_time":10.29615349},
{"learn":[0.1551740099],"iteration":672,"passed_time":21.12384003,"remaining_time":10.26373802},
{"learn":[0.1551437472],"iteration":673,"passed_time":21.1570977,"remaining_time":10.23325497},
{"learn":[0.1551069966],"iteration":674,"passed_time":21.1880305,"remaining_time":10.20164431},
{"learn":[0.1550521557],"iteration":675,"passed_time":21.2194887,"remaining_time":10.17028748},
{"learn":[0.1550434442],"iteration":676,"passed_time":21.30444129,"remaining_time":10.16445279},
{"learn":[0.155033468],"iteration":677,"passed_time":21.34300781,"remaining_time":10.13635474},
{"learn":[0.1549805179],"iteration":678,"passed_time":21.39236326,"remaining_time":10.11332637},
{"learn":[0.1549662862],"iteration":679,"passed_time":21.42269124,"remaining_time":10.08126647},
{"learn":[0.1549302746],"iteration":680,"passed_time":21.45919535,"remaining_time":10.05210473},
{"learn":[0.1549218618],"iteration":681,"passed_time":21.49005487,"remaining_time":10.02028951},
{"learn":[0.1548283109],"iteration":682,"passed_time":21.52239254,"remaining_time":9.989163154},
{"learn":[0.1548142225],"iteration":683,"passed_time":21.55186646,"remaining_time":9.956710237},
{"learn":[0.1547905972],"iteration":684,"passed_time":21.58414305,"remaining_time":9.925554831},
{"learn":[0.1547866828],"iteration":685,"passed_time":21.61356771,"remaining_time":9.893090761},
{"learn":[0.1546803799],"iteration":686,"passed_time":21.64917069,"remaining_time":9.863450401},
{"learn":[0.1546656323],"iteration":687,"passed_time":21.68480637,"remaining_time":9.833807541},
{"learn":[0.1546135818],"iteration":688,"passed_time":21.72145069,"remaining_time":9.804602559},
{"learn":[0.1545047244],"iteration":689,"passed_time":21.7521776,"remaining_time":9.772717473},
{"learn":[0.1544861021],"iteration":690,"passed_time":21.78293137,"remaining_time":9.740847746},
{"learn":[0.1544781784],"iteration":691,"passed_time":21.81620226,"remaining_time":9.710101586},
{"learn":[0.1544466594],"iteration":692,"passed_time":21.84746144,"remaining_time":9.678456944},
{"learn":[0.1544246313],"iteration":693,"passed_time":21.87935891,"remaining_time":9.64709485},
{"learn":[0.1543986532],"iteration":694,"passed_time":21.90768413,"remaining_time":9.614163539},
{"learn":[0.154330721],"iteration":695,"passed_time":21.93788413,"remaining_time":9.582064334},
{"learn":[0.1542934954],"iteration":696,"passed_time":21.96580368,"remaining_time":9.548979218},
{"learn":[0.1542374371],"iteration":697,"passed_time":21.99797822,"remaining_time":9.517749889},
{"learn":[0.154181594],"iteration":698,"passed_time":22.03097991,"remaining_time":9.486874037},
{"learn":[0.1541681295],"iteration":699,"passed_time":22.06078456,"remaining_time":9.454621954},
{"learn":[0.1541298088],"iteration":700,"passed_time":22.08991997,"remaining_time":9.4220914},
{"learn":[0.1540972271],"iteration":701,"passed_time":22.120069,"remaining_time":9.390000799},
{"learn":[0.1540641955],"iteration":702,"passed_time":22.15152338,"remaining_time":9.358467205},
{"learn":[0.1540430655],"iteration":703,"passed_time":22.18377221,"remaining_time":9.327267859},
{"learn":[0.154015621],"iteration":704,"passed_time":22.21379638,"remaining_time":9.295134655},
{"learn":[0.1539937186],"iteration":705,"passed_time":22.24414109,"remaining_time":9.263140908},
{"learn":[0.1539772386],"iteration":706,"passed_time":22.27133216,"remaining_time":9.229844871},
{"learn":[0.1539633179],"iteration":707,"passed_time":22.30167627,"remaining_time":9.197866482},
{"learn":[0.153918186],"iteration":708,"passed_time":22.33392721,"remaining_time":9.166675343},
{"learn":[0.1538734925],"iteration":709,"passed_time":22.36770989,"remaining_time":9.136106855},
{"learn":[0.1538535678],"iteration":710,"passed_time":22.39905336,"remaining_time":9.104537862},
{"learn":[0.153820136],"iteration":711,"passed_time":22.42646394,"remaining_time":9.071378674},
{"learn":[0.1537747054],"iteration":712,"passed_time":22.45299421,"remaining_time":9.037881261},
{"learn":[0.1537607952],"iteration":713,"passed_time":22.48067021,"remaining_time":9.004862299},
{"learn":[0.1537458878],"iteration":714,"passed_time":22.5056726,"remaining_time":8.970792573},
{"learn":[0.1537243423],"iteration":715,"passed_time":22.5351647,"remaining_time":8.938529015},
{"learn":[0.1536917977],"iteration":716,"passed_time":22.56392701,"remaining_time":8.905985137},
{"learn":[0.1536662623],"iteration":717,"passed_time":22.59267982,"remaining_time":8.873448061},
{"learn":[0.1536176964],"iteration":718,"passed_time":22.6211469,"remaining_time":8.840809847},
{"learn":[0.1536027507],"iteration":719,"passed_time":22.65234228,"remaining_time":8.809244221},
{"learn":[0.1535689646],"iteration":720,"passed_time":22.68493235,"remaining_time":8.778219315},
{"learn":[0.1535567185],"iteration":721,"passed_time":22.71224119,"remaining_time":8.745156581},
{"learn":[0.1535032066],"iteration":722,"passed_time":22.74798564,"remaining_time":8.715341664},
{"learn":[0.1534925855],"iteration":723,"passed_time":22.77949657,"remaining_time":8.683896481},
{"learn":[0.1534432234],"iteration":724,"passed_time":22.81872838,"remaining_time":8.655379729},
{"learn":[0.1534133496],"iteration":725,"passed_time":22.85158997,"remaining_time":8.624429273},
{"learn":[0.153392774],"iteration":726,"passed_time":22.88703758,"remaining_time":8.59444465},
{"learn":[0.1533673377],"iteration":727,"passed_time":22.92030413,"remaining_time":8.563630115},
{"learn":[0.1532865664],"iteration":728,"passed_time":22.95132564,"remaining_time":8.531974279},
{"learn":[0.1532677514],"iteration":729,"passed_time":22.984245,"remaining_time":8.501022125},
{"learn":[0.1532241342],"iteration":730,"passed_time":23.01870014,"remaining_time":8.470629738},
{"learn":[0.1531939005],"iteration":731,"passed_time":23.05036698,"remaining_time":8.439205396},
{"learn":[0.1531042591],"iteration":732,"passed_time":23.08312526,"remaining_time":8.408177958},
{"learn":[0.1530611499],"iteration":733,"passed_time":23.11470242,"remaining_time":8.376717772},
{"learn":[0.1530491696],"iteration":734,"passed_time":23.14857526,"remaining_time":8.346084958},
{"learn":[0.1530321265],"iteration":735,"passed_time":23.18154595,"remaining_time":8.315119743},
{"learn":[0.1529722071],"iteration":736,"passed_time":23.21564131,"remaining_time":8.284550426},
{"learn":[0.1529645687],"iteration":737,"passed_time":23.24385021,"remaining_time":8.251881781},
{"learn":[0.1529037782],"iteration":738,"passed_time":23.2770509,"remaining_time":8.220988207},
{"learn":[0.1528810687],"iteration":739,"passed_time":23.30875184,"remaining_time":8.189561458},
{"learn":[0.1528425186],"iteration":740,"passed_time":23.34634823,"remaining_time":8.160194591},
{"learn":[0.1528281651],"iteration":741,"passed_time":23.3820857,"remaining_time":8.13015918},
{"learn":[0.1528049654],"iteration":742,"passed_time":23.4140308,"remaining_time":8.098796656},
{"learn":[0.1527911928],"iteration":743,"passed_time":23.44446263,"remaining_time":8.066911873},
{"learn":[0.1527506696],"iteration":744,"passed_time":23.48244464,"remaining_time":8.037615279},
{"learn":[0.1527137765],"iteration":745,"passed_time":23.51490359,"remaining_time":8.006414895},
{"learn":[0.1526928482],"iteration":746,"passed_time":23.5463641,"remaining_time":7.974872982},
{"learn":[0.1526391092],"iteration":747,"passed_time":23.5832408,"remaining_time":7.945155991},
{"learn":[0.1526093211],"iteration":748,"passed_time":23.61547864,"remaining_time":7.913865338},
{"learn":[0.1525791265],"iteration":749,"passed_time":23.64903461,"remaining_time":7.883011538},
{"learn":[0.1525676039],"iteration":750,"passed_time":23.6812454,"remaining_time":7.851704534},
{"learn":[0.1525302513],"iteration":751,"passed_time":23.71314996,"remaining_time":7.820294136},
{"learn":[0.1525039766],"iteration":752,"passed_time":23.74268422,"remaining_time":7.788104918},
{"learn":[0.1524996257],"iteration":753,"passed_time":23.77120924,"remaining_time":7.755593467},
{"learn":[0.1524789634],"iteration":754,"passed_time":23.79965251,"remaining_time":7.723066047},
{"learn":[0.1524497391],"iteration":755,"passed_time":23.83223966,"remaining_time":7.691886873},
{"learn":[0.1524277311],"iteration":756,"passed_time":23.86641722,"remaining_time":7.661214511},
{"learn":[0.1523808704],"iteration":757,"passed_time":23.89895719,"remaining_time":7.63001008},
{"learn":[0.1523593115],"iteration":758,"passed_time":23.93174661,"remaining_time":7.598881335},
{"learn":[0.1523375688],"iteration":759,"passed_time":23.96048747,"remaining_time":7.566469729},
{"learn":[0.152308264],"iteration":760,"passed_time":23.99296412,"remaining_time":7.535241032},
{"learn":[0.152241617],"iteration":761,"passed_time":24.02876018,"remaining_time":7.50504583},
{"learn":[0.1522105794],"iteration":762,"passed_time":24.06238821,"remaining_time":7.474162523},
{"learn":[0.1521740445],"iteration":763,"passed_time":24.0961112,"remaining_time":7.443301366},
{"learn":[0.1521645894],"iteration":764,"passed_time":24.12718911,"remaining_time":7.411620184},
{"learn":[0.152129188],"iteration":765,"passed_time":24.16114721,"remaining_time":7.380820429},
{"learn":[0.1520797286],"iteration":766,"passed_time":24.19591937,"remaining_time":7.35025973},
{"learn":[0.1520595874],"iteration":767,"passed_time":24.22269459,"remaining_time":7.317272324},
{"learn":[0.1519443461],"iteration":768,"passed_time":24.25529257,"remaining_time":7.286050174},
{"learn":[0.1519279106],"iteration":769,"passed_time":24.28481709,"remaining_time":7.253906404},
{"learn":[0.1519092718],"iteration":770,"passed_time":24.31521376,"remaining_time":7.222028471},
{"learn":[0.1518731771],"iteration":771,"passed_time":24.344337,"remaining_time":7.189778285},
{"learn":[0.1518587018],"iteration":772,"passed_time":24.37361652,"remaining_time":7.157582083},
{"learn":[0.1517729918],"iteration":773,"passed_time":24.40412524,"remaining_time":7.125752331},
{"learn":[0.1517629029],"iteration":774,"passed_time":24.43339444,"remaining_time":7.093566128},
{"learn":[0.1517143346],"iteration":775,"passed_time":24.46700638,"remaining_time":7.062641015},
{"learn":[0.1516698427],"iteration":776,"passed_time":24.49655782,"remaining_time":7.030543622},
{"learn":[0.1515806146],"iteration":777,"passed_time":24.53037656,"remaining_time":6.999670431},
{"learn":[0.1515380406],"iteration":778,"passed_time":24.56084997,"remaining_time":6.967840621},
{"learn":[0.1515027987],"iteration":779,"passed_time":24.59391155,"remaining_time":6.936744282},
{"learn":[0.1514461285],"iteration":780,"passed_time":24.62847435,"remaining_time":6.906063869},
{"learn":[0.151399744],"iteration":781,"passed_time":24.65946564,"remaining_time":6.874377889},
{"learn":[0.1513597722],"iteration":782,"passed_time":24.69468407,"remaining_time":6.843865189},
{"learn":[0.1513266208],"iteration":783,"passed_time":24.72900699,"remaining_time":6.813093762},
{"learn":[0.1513058946],"iteration":784,"passed_time":24.76253088,"remaining_time":6.782094445},
{"learn":[0.1512518081],"iteration":785,"passed_time":24.79534854,"remaining_time":6.750896422},
{"learn":[0.1511632093],"iteration":786,"passed_time":24.82523824,"remaining_time":6.718901835},
{"learn":[0.1510847278],"iteration":787,"passed_time":24.8614392,"remaining_time":6.688610547},
{"learn":[0.1510552711],"iteration":788,"passed_time":24.89497581,"remaining_time":6.657591757},
{"learn":[0.1509472073],"iteration":789,"passed_time":24.93033689,"remaining_time":6.627051578},
{"learn":[0.1509243613],"iteration":790,"passed_time":24.96374977,"remaining_time":6.595984453},
{"learn":[0.1508943323],"iteration":791,"passed_time":24.99544652,"remaining_time":6.564460701},
{"learn":[0.1508708784],"iteration":792,"passed_time":25.02906793,"remaining_time":6.533438916},
{"learn":[0.1508640887],"iteration":793,"passed_time":25.05648159,"remaining_time":6.500800009},
{"learn":[0.150844842],"iteration":794,"passed_time":25.08850271,"remaining_time":6.469362335},
{"learn":[0.150823097],"iteration":795,"passed_time":25.11931641,"remaining_time":6.437613753},
{"learn":[0.150767679],"iteration":796,"passed_time":25.1547952,"remaining_time":6.407055742},
{"learn":[0.1506853158],"iteration":797,"passed_time":25.18718914,"remaining_time":6.375704519},
{"learn":[0.1506210465],"iteration":798,"passed_time":25.22260716,"remaining_time":6.345111437},
{"learn":[0.1505671655],"iteration":799,"passed_time":25.25461806,"remaining_time":6.313654514},
{"learn":[0.1505336628],"iteration":800,"passed_time":25.288643,"remaining_time":6.282696575},
{"learn":[0.1504925491],"iteration":801,"passed_time":25.3190646,"remaining_time":6.250841386},
{"learn":[0.150395298],"iteration":802,"passed_time":25.35138708,"remaining_time":6.219456108},
{"learn":[0.1503765108],"iteration":803,"passed_time":25.38128976,"remaining_time":6.187478599},
{"learn":[0.150360414],"iteration":804,"passed_time":25.41380667,"remaining_time":6.156139504},
{"learn":[0.1503146675],"iteration":805,"passed_time":25.44273952,"remaining_time":6.123934824},
{"learn":[0.1502780217],"iteration":806,"passed_time":25.47552812,"remaining_time":6.092660381},
{"learn":[0.1502354727],"iteration":807,"passed_time":25.50835885,"remaining_time":6.061392201},
{"learn":[0.1502070404],"iteration":808,"passed_time":25.53896009,"remaining_time":6.029593791},
{"learn":[0.1501670105],"iteration":809,"passed_time":25.57226634,"remaining_time":5.998432846},
{"learn":[0.1501106032],"iteration":810,"passed_time":25.60619029,"remaining_time":5.967410561},
{"learn":[0.1500828441],"iteration":811,"passed_time":25.63223262,"remaining_time":5.93455632},
{"learn":[0.1500448315],"iteration":812,"passed_time":25.66365433,"remaining_time":5.902956161},
{"learn":[0.1500233882],"iteration":813,"passed_time":25.69482564,"remaining_time":5.871299226},
{"learn":[0.1499460816],"iteration":814,"passed_time":25.72674376,"remaining_time":5.839813},
{"learn":[0.1499205114],"iteration":815,"passed_time":25.75669112,"remaining_time":5.807881331},
{"learn":[0.1498707075],"iteration":816,"passed_time":25.78785134,"remaining_time":5.776226187},
{"learn":[0.1498496013],"iteration":817,"passed_time":25.81336398,"remaining_time":5.743315702},
{"learn":[0.1498068959],"iteration":818,"passed_time":25.84345176,"remaining_time":5.711434394},
{"learn":[0.1497889349],"iteration":819,"passed_time":25.86943521,"remaining_time":5.678656509},
{"learn":[0.1497558435],"iteration":820,"passed_time":25.89743969,"remaining_time":5.646335816},
{"learn":[0.1497216285],"iteration":821,"passed_time":25.92593324,"remaining_time":5.614131529},
{"learn":[0.1496891785],"iteration":822,"passed_time":25.95619517,"remaining_time":5.582316579},
{"learn":[0.1496534867],"iteration":823,"passed_time":25.98480427,"remaining_time":5.550152368},
{"learn":[0.1496376494],"iteration":824,"passed_time":26.01405102,"remaining_time":5.518132035},
{"learn":[0.1495671923],"iteration":825,"passed_time":26.04473551,"remaining_time":5.486421282},
{"learn":[0.1495086121],"iteration":826,"passed_time":26.07410963,"remaining_time":5.454438894},
{"learn":[0.1494772598],"iteration":827,"passed_time":26.1033792,"remaining_time":5.422441089},
{"learn":[0.1494480082],"iteration":828,"passed_time":26.13456232,"remaining_time":5.390844581},
{"learn":[0.1494136067],"iteration":829,"passed_time":26.15899988,"remaining_time":5.357867446},
{"learn":[0.1493486883],"iteration":830,"passed_time":26.18890938,"remaining_time":5.326023689},
{"learn":[0.1493135528],"iteration":831,"passed_time":26.21823806,"remaining_time":5.294067301},
{"learn":[0.1492914072],"iteration":832,"passed_time":26.24701903,"remaining_time":5.262007416},
{"learn":[0.1492045974],"iteration":833,"passed_time":26.27966182,"remaining_time":5.230724055},
{"learn":[0.1491977717],"iteration":834,"passed_time":26.30606186,"remaining_time":5.198203841},
{"learn":[0.149148461],"iteration":835,"passed_time":26.3327775,"remaining_time":5.165760179},
{"learn":[0.1491159359],"iteration":836,"passed_time":26.34986709,"remaining_time":5.131455597},
{"learn":[0.1490569167],"iteration":837,"passed_time":26.36775481,"remaining_time":5.097346395},
{"learn":[0.1489936193],"iteration":838,"passed_time":26.39832669,"remaining_time":5.065709889},
{"learn":[0.1489659764],"iteration":839,"passed_time":26.43071722,"remaining_time":5.034422328},
{"learn":[0.1489138382],"iteration":840,"passed_time":26.46013193,"remaining_time":5.002569533},
{"learn":[0.148864662],"iteration":841,"passed_time":26.49406834,"remaining_time":4.971571018},
{"learn":[0.148846476],"iteration":842,"passed_time":26.5156772,"remaining_time":4.938269657},
{"learn":[0.1488059675],"iteration":843,"passed_time":26.53320353,"remaining_time":4.904241411},
{"learn":[0.1487659153],"iteration":844,"passed_time":26.55096341,"remaining_time":4.870295064},
{"learn":[0.1486576422],"iteration":845,"passed_time":26.58341914,"remaining_time":4.839062113},
{"learn":[0.1486051594],"iteration":846,"passed_time":26.61657176,"remaining_time":4.80795216},
{"learn":[0.1485856691],"iteration":847,"passed_time":26.6555746,"remaining_time":4.777886014},
{"learn":[0.1485469361],"iteration":848,"passed_time":26.69113618,"remaining_time":4.747186765},
{"learn":[0.1484891751],"iteration":849,"passed_time":26.73074693,"remaining_time":4.717190634},
{"learn":[0.148470151],"iteration":850,"passed_time":26.76468801,"remaining_time":4.686179217},
{"learn":[0.1484315996],"iteration":851,"passed_time":26.79880631,"remaining_time":4.655191707},
{"learn":[0.1483958299],"iteration":852,"passed_time":26.83209674,"remaining_time":4.624054186},
{"learn":[0.1483768117],"iteration":853,"passed_time":26.86456707,"remaining_time":4.59277142},
{"learn":[0.1483536344],"iteration":854,"passed_time":26.89695322,"remaining_time":4.561471599},
{"learn":[0.1483301729],"iteration":855,"passed_time":26.92750478,"remaining_time":4.529860617},
{"learn":[0.1483116419],"iteration":856,"passed_time":26.96134721,"remaining_time":4.498801226},
{"learn":[0.1482470416],"iteration":857,"passed_time":27.00336924,"remaining_time":4.469089082},
{"learn":[0.1482371563],"iteration":858,"passed_time":27.03949016,"remaining_time":4.438379643},
{"learn":[0.1482156648],"iteration":859,"passed_time":27.09403422,"remaining_time":4.410656734},
{"learn":[0.1481689068],"iteration":860,"passed_time":27.12827568,"remaining_time":4.379593868},
{"learn":[0.1481422462],"iteration":861,"passed_time":27.16075252,"remaining_time":4.348241123},
{"learn":[0.1481316377],"iteration":862,"passed_time":27.19365508,"remaining_time":4.316953356},
{"learn":[0.1481009282],"iteration":863,"passed_time":27.22588722,"remaining_time":4.285556321},
{"learn":[0.1480378407],"iteration":864,"passed_time":27.25675183,"remaining_time":4.253943926},
{"learn":[0.1480098092],"iteration":865,"passed_time":27.28551633,"remaining_time":4.2220083},
{"learn":[0.1479810362],"iteration":866,"passed_time":27.31565461,"remaining_time":4.19029073},
{"learn":[0.1479509139],"iteration":867,"passed_time":27.34673562,"remaining_time":4.158720163},
{"learn":[0.1479083842],"iteration":868,"passed_time":27.37405053,"remaining_time":4.126582991},
{"learn":[0.1478559589],"iteration":869,"passed_time":27.40495078,"remaining_time":4.094992645},
{"learn":[0.1478254013],"iteration":870,"passed_time":27.43907481,"remaining_time":4.063881343},
{"learn":[0.1477911997],"iteration":871,"passed_time":27.47444683,"remaining_time":4.032946323},
{"learn":[0.1477508245],"iteration":872,"passed_time":27.5084581,"remaining_time":4.001803183},
{"learn":[0.1477184336],"iteration":873,"passed_time":27.5415169,"remaining_time":3.970516167},
{"learn":[0.1476805042],"iteration":874,"passed_time":27.57471304,"remaining_time":3.93924472},
{"learn":[0.1476384281],"iteration":875,"passed_time":27.60694325,"remaining_time":3.907832149},
{"learn":[0.1476204996],"iteration":876,"passed_time":27.64164483,"remaining_time":3.876764327},
{"learn":[0.1475556029],"iteration":877,"passed_time":27.67598604,"remaining_time":3.845638152},
{"learn":[0.1475392878],"iteration":878,"passed_time":27.70989947,"remaining_time":3.814445775},
{"learn":[0.1474919638],"iteration":879,"passed_time":27.73791798,"remaining_time":3.782443361},
{"learn":[0.1474455675],"iteration":880,"passed_time":27.77399817,"remaining_time":3.751538912},
{"learn":[0.1474092411],"iteration":881,"passed_time":27.80306779,"remaining_time":3.719684806},
{"learn":[0.1473727781],"iteration":882,"passed_time":27.83297162,"remaining_time":3.687947542},
{"learn":[0.1473478624],"iteration":883,"passed_time":27.86202177,"remaining_time":3.656102404},
{"learn":[0.1473275302],"iteration":884,"passed_time":27.88997542,"remaining_time":3.6241211},
{"learn":[0.147310999],"iteration":885,"passed_time":27.92372158,"remaining_time":3.592894199},
{"learn":[0.1472848095],"iteration":886,"passed_time":27.95462958,"remaining_time":3.561300047},
{"learn":[0.1472452109],"iteration":887,"passed_time":27.98500422,"remaining_time":3.529640171},
{"learn":[0.1472148728],"iteration":888,"passed_time":28.00253811,"remaining_time":3.496379899},
{"learn":[0.1471820756],"iteration":889,"passed_time":28.01860212,"remaining_time":3.462973296},
{"learn":[0.1471663617],"iteration":890,"passed_time":28.03360276,"remaining_time":3.429475535},
{"learn":[0.1471443937],"iteration":891,"passed_time":28.06123064,"remaining_time":3.397548104},
{"learn":[0.1471256608],"iteration":892,"passed_time":28.09868994,"remaining_time":3.366808313},
{"learn":[0.1470979616],"iteration":893,"passed_time":28.14002585,"remaining_time":3.336513133},
{"learn":[0.1470851916],"iteration":894,"passed_time":28.17617682,"remaining_time":3.30558499},
{"learn":[0.1470697189],"iteration":895,"passed_time":28.201712,"remaining_time":3.273413},
{"learn":[0.1470617616],"iteration":896,"passed_time":28.23748633,"remaining_time":3.242431541},
{"learn":[0.147033654],"iteration":897,"passed_time":28.2734112,"remaining_time":3.211456506},
{"learn":[0.1470174017],"iteration":898,"passed_time":28.30720766,"remaining_time":3.180231339},
{"learn":[0.1470064585],"iteration":899,"passed_time":28.33731133,"remaining_time":3.148590148},
{"learn":[0.1469905117],"iteration":900,"passed_time":28.36792968,"remaining_time":3.117008921},
{"learn":[0.1469555441],"iteration":901,"passed_time":28.40312711,"remaining_time":3.085927336},
{"learn":[0.1469472515],"iteration":902,"passed_time":28.43486707,"remaining_time":3.054465234},
{"learn":[0.1469327265],"iteration":903,"passed_time":28.4695337,"remaining_time":3.023313313},
{"learn":[0.1469037367],"iteration":904,"passed_time":28.50729423,"remaining_time":2.992478399},
{"learn":[0.1468629139],"iteration":905,"passed_time":28.54585258,"remaining_time":2.961710974},
{"learn":[0.1468377995],"iteration":906,"passed_time":28.58401449,"remaining_time":2.930885719},
{"learn":[0.1468153033],"iteration":907,"passed_time":28.61549521,"remaining_time":2.899367356},
{"learn":[0.1467931707],"iteration":908,"passed_time":28.64725347,"remaining_time":2.867876861},
{"learn":[0.1467548004],"iteration":909,"passed_time":28.68219866,"remaining_time":2.836700966},
{"learn":[0.1467319474],"iteration":910,"passed_time":28.71536931,"remaining_time":2.805343435},
{"learn":[0.1467059849],"iteration":911,"passed_time":28.74962374,"remaining_time":2.774086501},
{"learn":[0.1466801084],"iteration":912,"passed_time":28.78253738,"remaining_time":2.742695237},
{"learn":[0.1466431805],"iteration":913,"passed_time":28.81849303,"remaining_time":2.711586871},
{"learn":[0.1466072366],"iteration":914,"passed_time":28.85197145,"remaining_time":2.680237785},
{"learn":[0.14658007],"iteration":915,"passed_time":28.8859653,"remaining_time":2.648931316},
{"learn":[0.1465616181],"iteration":916,"passed_time":28.9203409,"remaining_time":2.617653538},
{"learn":[0.1465478145],"iteration":917,"passed_time":28.95274568,"remaining_time":2.586192969},
{"learn":[0.1465296029],"iteration":918,"passed_time":28.98427827,"remaining_time":2.554653471},
{"learn":[0.1465080186],"iteration":919,"passed_time":29.01340384,"remaining_time":2.522904682},
{"learn":[0.1464688932],"iteration":920,"passed_time":29.04523419,"remaining_time":2.491393595},
{"learn":[0.1464331599],"iteration":921,"passed_time":29.07881626,"remaining_time":2.460030009},
{"learn":[0.1463971318],"iteration":922,"passed_time":29.11566387,"remaining_time":2.428934039},
{"learn":[0.1463852979],"iteration":923,"passed_time":29.15050935,"remaining_time":2.397660942},
{"learn":[0.1463552788],"iteration":924,"passed_time":29.19082382,"remaining_time":2.366823553},
{"learn":[0.1463322552],"iteration":925,"passed_time":29.22506246,"remaining_time":2.335480153},
{"learn":[0.146302036],"iteration":926,"passed_time":29.25914596,"remaining_time":2.30411829},
{"learn":[0.1462541195],"iteration":927,"passed_time":29.29392858,"remaining_time":2.272804803},
{"learn":[0.1462217998],"iteration":928,"passed_time":29.31208571,"remaining_time":2.240213225},
{"learn":[0.1461789037],"iteration":929,"passed_time":29.33401418,"remaining_time":2.207936551},
{"learn":[0.1461653835],"iteration":930,"passed_time":29.3695141,"remaining_time":2.176687941},
{"learn":[0.1461439919],"iteration":931,"passed_time":29.4036177,"remaining_time":2.14532833},
{"learn":[0.146113937],"iteration":932,"passed_time":29.44209926,"remaining_time":2.114277224},
{"learn":[0.1460779301],"iteration":933,"passed_time":29.47143329,"remaining_time":2.082563809},
{"learn":[0.1460529063],"iteration":934,"passed_time":29.50049673,"remaining_time":2.050836671},
{"learn":[0.146009662],"iteration":935,"passed_time":29.53776189,"remaining_time":2.019676027},
{"learn":[0.1459899351],"iteration":936,"passed_time":29.57003746,"remaining_time":1.988166873},
{"learn":[0.1459790806],"iteration":937,"passed_time":29.60180593,"remaining_time":1.956622567},
{"learn":[0.1459418372],"iteration":938,"passed_time":29.63643338,"remaining_time":1.92526351},
{"learn":[0.1459200887],"iteration":939,"passed_time":29.67032493,"remaining_time":1.893850527},
{"learn":[0.1458816211],"iteration":940,"passed_time":29.70108582,"remaining_time":1.862235987},
{"learn":[0.1458535496],"iteration":941,"passed_time":29.73442664,"remaining_time":1.830782107},
{"learn":[0.1458270439],"iteration":942,"passed_time":29.76402294,"remaining_time":1.799097887},
{"learn":[0.1457819907],"iteration":943,"passed_time":29.79267332,"remaining_time":1.767361977},
{"learn":[0.1457552842],"iteration":944,"passed_time":29.82872005,"remaining_time":1.736063071},
{"learn":[0.1457388351],"iteration":945,"passed_time":29.85703838,"remaining_time":1.704312973},
{"learn":[0.1457243126],"iteration":946,"passed_time":29.88614018,"remaining_time":1.67261397},
{"learn":[0.1456897615],"iteration":947,"passed_time":29.91509354,"remaining_time":1.640912304},
{"learn":[0.1456751047],"iteration":948,"passed_time":29.94182457,"remaining_time":1.609097},
{"learn":[0.1456422763],"iteration":949,"passed_time":29.97005296,"remaining_time":1.577371208},
{"learn":[0.1456123755],"iteration":950,"passed_time":29.99687142,"remaining_time":1.545580126},
{"learn":[0.1456024231],"iteration":951,"passed_time":30.02732554,"remaining_time":1.5139828},
{"learn":[0.1455813719],"iteration":952,"passed_time":30.05667295,"remaining_time":1.482333293},
{"learn":[0.1455560072],"iteration":953,"passed_time":30.08399465,"remaining_time":1.450590937},
{"learn":[0.1455340269],"iteration":954,"passed_time":30.11325993,"remaining_time":1.418949421},
{"learn":[0.1455079976],"iteration":955,"passed_time":30.14325779,"remaining_time":1.387346593},
{"learn":[0.1454617094],"iteration":956,"passed_time":30.17454025,"remaining_time":1.355804839},
{"learn":[0.1454463922],"iteration":957,"passed_time":30.20440643,"remaining_time":1.324201534},
{"learn":[0.145405583],"iteration":958,"passed_time":30.23436485,"remaining_time":1.292605797},
{"learn":[0.1453914174],"iteration":959,"passed_time":30.26380598,"remaining_time":1.260991916},
{"learn":[0.1453751714],"iteration":960,"passed_time":30.29258639,"remaining_time":1.229355743},
{"learn":[0.1453558463],"iteration":961,"passed_time":30.32433488,"remaining_time":1.19784275},
{"learn":[0.1453495648],"iteration":962,"passed_time":30.35173431,"remaining_time":1.16616217},
{"learn":[0.1453244382],"iteration":963,"passed_time":30.3853643,"remaining_time":1.134723148},
{"learn":[0.1452972364],"iteration":964,"passed_time":30.41750484,"remaining_time":1.103225564},
{"learn":[0.1452517337],"iteration":965,"passed_time":30.44699245,"remaining_time":1.071633275},
{"learn":[0.1452178726],"iteration":966,"passed_time":30.47275789,"remaining_time":1.039918315},
{"learn":[0.1452015807],"iteration":967,"passed_time":30.50302481,"remaining_time":1.008364457},
{"learn":[0.145178043],"iteration":968,"passed_time":30.53196131,"remaining_time":0.976770692},
{"learn":[0.1451717523],"iteration":969,"passed_time":30.56016158,"remaining_time":0.9451596364},
{"learn":[0.1451572304],"iteration":970,"passed_time":30.59064997,"remaining_time":0.9136239435},
{"learn":[0.145101236],"iteration":971,"passed_time":30.6207388,"remaining_time":0.8820788955},
{"learn":[0.1450850085],"iteration":972,"passed_time":30.64851169,"remaining_time":0.8504725752},
{"learn":[0.1450588237],"iteration":973,"passed_time":30.67626374,"remaining_time":0.81887357},
{"learn":[0.1450480689],"iteration":974,"passed_time":30.70523855,"remaining_time":0.7873138091},
{"learn":[0.1450434288],"iteration":975,"passed_time":30.73290511,"remaining_time":0.7557271748},
{"learn":[0.1450270201],"iteration":976,"passed_time":30.76460051,"remaining_time":0.7242434102},
{"learn":[0.1449952411],"iteration":977,"passed_time":30.79304928,"remaining_time":0.6926861802},
{"learn":[0.1449406841],"iteration":978,"passed_time":30.82828266,"remaining_time":0.6612808334},
{"learn":[0.1448994251],"iteration":979,"passed_time":30.86673333,"remaining_time":0.6299333333},
{"learn":[0.1448726294],"iteration":980,"passed_time":30.90720949,"remaining_time":0.5986105814},
{"learn":[0.1448540191],"iteration":981,"passed_time":30.94619405,"remaining_time":0.5672418461},
{"learn":[0.1448230249],"iteration":982,"passed_time":30.98109012,"remaining_time":0.5357869095},
{"learn":[0.1447857249],"iteration":983,"passed_time":31.0189949,"remaining_time":0.5043739008},
{"learn":[0.1447626399],"iteration":984,"passed_time":31.05928351,"remaining_time":0.4729840129},
{"learn":[0.1447490717],"iteration":985,"passed_time":31.09525159,"remaining_time":0.4415147285},
{"learn":[0.1447294593],"iteration":986,"passed_time":31.12628361,"remaining_time":0.4099713141},
{"learn":[0.1446806934],"iteration":987,"passed_time":31.16126364,"remaining_time":0.3784768863},
{"learn":[0.1446448603],"iteration":988,"passed_time":31.20055976,"remaining_time":0.3470234149},
{"learn":[0.1446122957],"iteration":989,"passed_time":31.22783364,"remaining_time":0.315432663},
{"learn":[0.1445652033],"iteration":990,"passed_time":31.25894412,"remaining_time":0.2838854663},
{"learn":[0.14453414],"iteration":991,"passed_time":31.29139284,"remaining_time":0.2523499423},
{"learn":[0.1445090836],"iteration":992,"passed_time":31.32419902,"remaining_time":0.2208150989},
{"learn":[0.1444748515],"iteration":993,"passed_time":31.35446466,"remaining_time":0.1892623622},
{"learn":[0.1444385721],"iteration":994,"passed_time":31.38963966,"remaining_time":0.1577368827},
{"learn":[0.1444217702],"iteration":995,"passed_time":31.42005678,"remaining_time":0.126184967},
{"learn":[0.1443715093],"iteration":996,"passed_time":31.45191075,"remaining_time":0.09463965121},
{"learn":[0.1443358929],"iteration":997,"passed_time":31.48367026,"remaining_time":0.06309352757},
{"learn":[0.1443049031],"iteration":998,"passed_time":31.51695386,"remaining_time":0.03154850236},
{"learn":[0.1442794743],"iteration":999,"passed_time":31.54822714,"remaining_time":0}
]}